{
  "id": "CTXGj",
  "name": "New Episode",
  "date": "2025-05-10T03:53:00.132+00:00",
  "scheduledTime": {
    "s": "2025-05-10T03:53:00.132+00:00",
    "e": "2025-05-10T08:53:00.132+00:00",
    "invalid": null,
    "isLuxonInterval": true
  },
  "tags": {
    "_type": "Tags",
    "value": [
      "active"
    ]
  },
  "actions": [
    {
      "id": "pzr-F",
      "round": 2,
      "societyId": "et0k8",
      "resourceIds": [],
      "texts": [],
      "risk": "1",
      "advantage": "1",
      "disadvantage": "Dis 0",
      "result": [],
      "voteTime": "2025-05-23T19:28:12.818+00:00",
      "status": "invalid",
      "tags": {
        "_type": "Tags",
        "value": []
      }
    },
    {
      "id": "Mjt4w",
      "round": 2,
      "societyId": "V9xbw",
      "resourceIds": [],
      "texts": [],
      "risk": 1,
      "advantage": 0,
      "disadvantage": 0,
      "result": [],
      "status": "open",
      "tags": {
        "_type": "Tags",
        "value": []
      }
    },
    {
      "id": "iTkZy",
      "round": 2,
      "societyId": "Feay0",
      "resourceIds": [
        "zj1sr"
      ],
      "texts": [
        "",
        ""
      ],
      "risk": "1",
      "advantage": "0",
      "disadvantage": "0",
      "result": [],
      "voteTime": "2025-05-23T19:15:18.818+00:00",
      "status": "invalid",
      "tags": {
        "_type": "Tags",
        "value": [
          "committed",
          "voted",
          "invalid"
        ]
      }
    },
    {
      "id": "jk75L",
      "round": 2,
      "societyId": "e-JcG",
      "resourceIds": [],
      "texts": [],
      "risk": 1,
      "advantage": 0,
      "disadvantage": 0,
      "result": [],
      "status": "open",
      "tags": {
        "_type": "Tags",
        "value": []
      }
    },
    {
      "id": "VmMzV",
      "round": 2,
      "societyId": "yXHVO",
      "resourceIds": [],
      "texts": [
        "",
        ""
      ],
      "risk": "1",
      "advantage": "0",
      "disadvantage": "0",
      "result": [],
      "voteTime": "2025-05-23T22:01:32.805+00:00",
      "status": "voted",
      "tags": {
        "_type": "Tags",
        "value": []
      }
    },
    {
      "id": "zCz57",
      "round": 1,
      "societyId": "et0k8",
      "resourceIds": [
        "HOzO6"
      ],
      "texts": [
        "dddddd",
        "",
        ""
      ],
      "risk": "1",
      "advantage": 0,
      "disadvantage": 0,
      "result": [],
      "status": "open",
      "tags": {
        "_type": "Tags",
        "value": []
      }
    },
    {
      "id": "Dh8rS",
      "round": 1,
      "societyId": "V9xbw",
      "resourceIds": [],
      "texts": [],
      "risk": 1,
      "advantage": 0,
      "disadvantage": 0,
      "result": [],
      "status": "open",
      "tags": {
        "_type": "Tags",
        "value": []
      }
    },
    {
      "id": "EWAp2",
      "round": 1,
      "societyId": "Feay0",
      "resourceIds": [
        "oxn07"
      ],
      "texts": [
        "",
        ""
      ],
      "risk": "1",
      "advantage": 0,
      "disadvantage": 0,
      "result": [],
      "status": "open",
      "tags": {
        "_type": "Tags",
        "value": []
      }
    },
    {
      "id": "Qkdxy",
      "round": 1,
      "societyId": "e-JcG",
      "resourceIds": [],
      "texts": [
        ""
      ],
      "risk": "1",
      "advantage": 0,
      "disadvantage": 0,
      "result": [],
      "status": "open",
      "tags": {
        "_type": "Tags",
        "value": []
      }
    },
    {
      "id": "jrAz3",
      "round": 1,
      "societyId": "yXHVO",
      "resourceIds": [],
      "texts": [],
      "risk": 1,
      "advantage": 0,
      "disadvantage": 0,
      "result": [],
      "status": "open",
      "tags": {
        "_type": "Tags",
        "value": []
      }
    },
    {
      "id": "vISYl",
      "round": "2",
      "societyId": "Feay0",
      "resourceIds": [
        "zj1sr",
        "Mqfth"
      ],
      "texts": [
        "",
        "",
        ""
      ],
      "risk": "1",
      "advantage": "0",
      "disadvantage": "0",
      "result": [],
      "voteTime": "2025-05-23T18:48:17.183+00:00",
      "status": "invalid",
      "tags": {
        "_type": "Tags",
        "value": [
          "committed",
          "invalid",
          "voted"
        ]
      }
    },
    {
      "id": "do6_p",
      "round": "2",
      "societyId": "Feay0",
      "resourceIds": [
        "Mqfth"
      ],
      "texts": [
        "",
        ""
      ],
      "risk": "1",
      "advantage": "0",
      "disadvantage": "0",
      "result": [],
      "voteTime": "2025-05-23T19:00:00.965+00:00",
      "status": "invalid",
      "tags": {
        "_type": "Tags",
        "value": [
          "voted",
          "invalid"
        ]
      }
    },
    {
      "id": "LsBu2",
      "round": "2",
      "societyId": "Feay0",
      "resourceIds": [
        "wRedp",
        "Mqfth"
      ],
      "texts": [
        "",
        "",
        ""
      ],
      "risk": "1",
      "advantage": "0",
      "disadvantage": "0",
      "result": [],
      "voteTime": "2025-05-23T19:00:19.536+00:00",
      "status": "invalid",
      "tags": {
        "_type": "Tags",
        "value": [
          "voted"
        ]
      }
    },
    {
      "id": "iJ-3k",
      "round": "2",
      "societyId": "Feay0",
      "resourceIds": [],
      "texts": [],
      "risk": 1,
      "advantage": 0,
      "disadvantage": 0,
      "result": [],
      "status": "invalid",
      "tags": {
        "_type": "Tags",
        "value": []
      }
    },
    {
      "id": "XPSBA",
      "round": "2",
      "societyId": "Feay0",
      "resourceIds": [
        "oxn07"
      ],
      "texts": [
        "try again",
        ""
      ],
      "risk": "1",
      "advantage": "0",
      "disadvantage": "0",
      "result": [],
      "voteTime": "2025-05-23T19:27:54.948+00:00",
      "status": "invalid",
      "tags": {
        "_type": "Tags",
        "value": []
      }
    },
    {
      "id": "B_pLW",
      "round": "2",
      "societyId": "et0k8",
      "resourceIds": [
        "JvqsG",
        "HOzO6"
      ],
      "texts": [
        "fsggsdgre",
        "dsgsrrae",
        ""
      ],
      "risk": 1,
      "advantage": 0,
      "disadvantage": 0,
      "result": [],
      "voteTime": "2025-05-28T14:31:53.179+00:00",
      "status": "invalid",
      "tags": {
        "_type": "Tags",
        "value": []
      }
    },
    {
      "id": "qx50W",
      "round": "3",
      "societyId": "et0k8",
      "resourceIds": [
        "JvqsG"
      ],
      "texts": [
        "airfare"
      ],
      "risk": "1",
      "advantage": "Adv 0",
      "disadvantage": "Dis 0",
      "result": [],
      "voteTime": "2025-05-25T23:44:53.602+00:00",
      "status": "voted",
      "tags": {
        "_type": "Tags",
        "value": []
      }
    },
    {
      "id": "cxA76",
      "round": "2",
      "societyId": "Feay0",
      "resourceIds": [
        "psJiM"
      ],
      "texts": [
        ""
      ],
      "risk": "1",
      "advantage": "Adv 0",
      "disadvantage": "2",
      "result": [],
      "voteTime": "2025-05-23T21:51:41.110+00:00",
      "status": "invalid",
      "tags": {
        "_type": "Tags",
        "value": []
      }
    },
    {
      "id": "gIzO5",
      "round": "2",
      "societyId": "Feay0",
      "resourceIds": [
        "AwCCh",
        "h463E"
      ],
      "texts": [
        "aergar",
        "sgrtgsret",
        ""
      ],
      "risk": "1",
      "advantage": "0",
      "disadvantage": "0",
      "result": [],
      "voteTime": "2025-05-23T22:05:30.161+00:00",
      "status": "invalid",
      "tags": {
        "_type": "Tags",
        "value": []
      }
    },
    {
      "id": "fnRCI",
      "round": "3",
      "societyId": "V9xbw",
      "resourceIds": [
        "FADd2"
      ],
      "texts": [
        ""
      ],
      "risk": "1",
      "advantage": "0",
      "disadvantage": "0",
      "result": [],
      "status": "open",
      "tags": {
        "_type": "Tags",
        "value": []
      }
    },
    {
      "id": "PJu6m",
      "round": "2",
      "societyId": "et0k8",
      "resourceIds": [
        "QvweM"
      ],
      "texts": [
        "test test",
        ""
      ],
      "result": [],
      "voteTime": "2025-05-28T19:12:24.827+00:00",
      "status": "voted",
      "tags": {
        "_type": "Tags",
        "value": []
      }
    },
    {
      "id": "IJJCb",
      "round": "2",
      "societyId": "Feay0",
      "resourceIds": [
        "FADd2"
      ],
      "texts": [
        "hi",
        ""
      ],
      "result": [],
      "voteTime": "2025-05-28T19:16:07.585+00:00",
      "status": "invalid",
      "tags": {
        "_type": "Tags",
        "value": []
      }
    },
    {
      "id": "II0iK",
      "round": "2",
      "societyId": "Feay0",
      "resourceIds": [
        "h463E"
      ],
      "texts": [
        "bew",
        ""
      ],
      "result": [],
      "voteTime": "2025-05-28T19:16:51.511+00:00",
      "status": "voted",
      "tags": {
        "_type": "Tags",
        "value": []
      }
    },
    {
      "id": "AdAhv",
      "round": "3",
      "societyId": "yXHVO",
      "resourceIds": [],
      "texts": [],
      "risk": 1,
      "advantage": 0,
      "disadvantage": 0,
      "result": [],
      "status": "open",
      "tags": {
        "_type": "Tags",
        "value": []
      }
    }
  ],
  "communities": [
    {
      "id": "o7kHM",
      "societyId": [
        "et0k8",
        "Feay0"
      ],
      "name": "Wizened Youth",
      "voice": "people",
      "tags": {
        "_type": "Tags",
        "value": []
      }
    },
    {
      "id": "Qw0Xm",
      "societyId": "et0k8",
      "ambassadorSocietyId": "",
      "player": "Jim (he/him)",
      "name": "Calendar Daddies",
      "voice": "leader",
      "tags": {
        "_type": "Tags",
        "value": []
      }
    },
    {
      "id": "lHvo5",
      "societyId": "V9xbw",
      "ambassadorSocietyId": "",
      "player": "",
      "name": "ribs",
      "voice": "leader",
      "tags": {
        "_type": "Tags",
        "value": []
      }
    },
    {
      "id": "UDMgC",
      "societyId": "et0k8",
      "ambassadorSocietyId": "",
      "player": "Bobby",
      "name": "Jeffrey Bezos",
      "voice": "people",
      "tags": {
        "_type": "Tags",
        "value": []
      }
    },
    {
      "id": "B95dD",
      "societyId": "et0k8",
      "ambassadorSocietyId": "",
      "player": "Jason",
      "name": "Dirty Harries",
      "voice": "leader",
      "tags": {
        "_type": "Tags",
        "value": []
      }
    },
    {
      "id": "cV-Kn",
      "societyId": "et0k8",
      "ambassadorSocietyId": "",
      "player": "Fredrick",
      "name": "Elders",
      "voice": "people",
      "tags": {
        "_type": "Tags",
        "value": []
      }
    },
    {
      "id": "LiQVN",
      "societyId": "et0k8",
      "ambassadorSocietyId": "",
      "player": "Jeff",
      "name": "Pencils Down",
      "voice": "people",
      "tags": {
        "_type": "Tags",
        "value": []
      }
    },
    {
      "id": "R9tmF",
      "societyId": "et0k8",
      "name": "Quinn",
      "voice": "people",
      "tags": {
        "_type": "Tags",
        "value": []
      }
    },
    {
      "id": "kATHn",
      "societyId": "et0k8",
      "name": "Jimmy",
      "voice": "people",
      "tags": {
        "_type": "Tags",
        "value": []
      }
    },
    {
      "id": "G_9_r",
      "societyId": "Feay0",
      "ambassadorSocietyId": "",
      "player": "",
      "name": "nana",
      "voice": "people",
      "tags": {
        "_type": "Tags",
        "value": []
      }
    },
    {
      "id": "ssnLF",
      "societyId": "Feay0",
      "ambassadorSocietyId": "",
      "player": "",
      "name": "baba",
      "voice": "leader",
      "tags": {
        "_type": "Tags",
        "value": []
      }
    },
    {
      "id": "FRomU",
      "societyId": "Feay0",
      "ambassadorSocietyId": "",
      "player": "",
      "name": "gaga",
      "voice": "people",
      "tags": {
        "_type": "Tags",
        "value": []
      }
    },
    {
      "id": "NzLOs",
      "societyId": "Feay0",
      "ambassadorSocietyId": "",
      "player": "Hi",
      "name": "dada",
      "voice": "leader",
      "tags": {
        "_type": "Tags",
        "value": []
      }
    },
    {
      "id": "NVQbL",
      "societyId": "Feay0",
      "ambassadorSocietyId": "",
      "player": "",
      "name": "popo",
      "voice": "people",
      "tags": {
        "_type": "Tags",
        "value": []
      }
    },
    {
      "id": "u0fa0",
      "societyId": "e-JcG",
      "ambassadorSocietyId": "",
      "player": "",
      "name": "skreeee",
      "voice": "people",
      "tags": {
        "_type": "Tags",
        "value": [
          "endangered"
        ]
      }
    },
    {
      "id": "jaCtF",
      "societyId": "yXHVO",
      "ambassadorSocietyId": "",
      "player": "",
      "name": "big ol shair",
      "voice": "people",
      "tags": {
        "_type": "Tags",
        "value": []
      }
    },
    {
      "id": "Bd8RN",
      "societyId": "V9xbw",
      "ambassadorSocietyId": "",
      "player": "",
      "name": "My Guys",
      "voice": "people",
      "tags": {
        "_type": "Tags",
        "value": [
          "endangered"
        ]
      }
    },
    {
      "id": "g-uC_",
      "societyId": "et0k8",
      "ambassadorSocietyId": "",
      "player": "Person (they/them)",
      "name": "Test",
      "voice": "leader",
      "tags": {
        "_type": "Tags",
        "value": []
      }
    },
    {
      "id": "PIBFt",
      "societyId": "yXHVO",
      "player": "me",
      "name": "hi",
      "voice": "leader",
      "tags": {
        "_type": "Tags",
        "value": []
      }
    },
    {
      "id": "SEm5M",
      "societyId": "yXHVO",
      "ambassadorSocietyId": "",
      "player": "",
      "name": "ok",
      "voice": "people",
      "tags": {
        "_type": "Tags",
        "value": []
      }
    }
  ],
  "phases": [
    {
      "id": "KN4Rt",
      "type": "Setup/Onboarding",
      "status": "complete",
      "round": 0,
      "duration": 1065,
      "timeElapsed": 28.01900000000001,
      "actualTime": {
        "s": "2025-05-28T19:22:46.449+00:00",
        "e": "2025-05-28T19:23:14.505+00:00",
        "invalid": null,
        "isLuxonInterval": true
      },
      "tags": {
        "_type": "Tags",
        "value": []
      }
    },
    {
      "id": "TW6li",
      "type": "Universal Phase",
      "status": "complete",
      "round": 1,
      "duration": 240,
      "timeElapsed": 174.15800000000033,
      "actualTime": {
        "s": "2025-05-13T23:51:02.029+00:00",
        "e": "2025-05-28T19:23:14.941+00:00",
        "invalid": null,
        "isLuxonInterval": true
      },
      "tags": {
        "_type": "Tags",
        "value": []
      }
    },
    {
      "id": "r5gob",
      "type": "Societal Phase",
      "status": "complete",
      "round": 1,
      "duration": 900,
      "timeElapsed": 0,
      "actualTime": {
        "s": "2025-05-10T03:53:00.133+00:00",
        "e": "2025-05-28T19:24:04.329+00:00",
        "invalid": null,
        "isLuxonInterval": true
      },
      "tags": {
        "_type": "Tags",
        "value": []
      }
    },
    {
      "id": "qveE2",
      "type": "Galactic Phase",
      "status": "complete",
      "round": 1,
      "duration": 720,
      "timeElapsed": 42.023999999999994,
      "actualTime": {
        "s": "2025-05-28T19:23:16.636+00:00",
        "e": "2025-05-28T19:24:05.025+00:00",
        "invalid": null,
        "isLuxonInterval": true
      },
      "tags": {
        "_type": "Tags",
        "value": []
      }
    },
    {
      "id": "ml6Q3",
      "type": "Universal Phase",
      "status": "complete",
      "round": 2,
      "duration": 240,
      "timeElapsed": 19.018,
      "actualTime": {
        "s": "2025-05-10T20:26:21.020+00:00",
        "e": "2025-05-28T19:24:05.710+00:00",
        "invalid": null,
        "isLuxonInterval": true
      },
      "tags": {
        "_type": "Tags",
        "value": []
      }
    },
    {
      "id": "BJ7S8",
      "type": "Societal Phase",
      "status": "complete",
      "round": 2,
      "duration": 660,
      "timeElapsed": 73.05700000000002,
      "actualTime": {
        "s": "2025-05-20T23:35:24.461+00:00",
        "e": "2025-05-28T19:24:06.341+00:00",
        "invalid": null,
        "isLuxonInterval": true
      },
      "tags": {
        "_type": "Tags",
        "value": []
      }
    },
    {
      "id": "ao-zv",
      "type": "Galactic Phase",
      "status": "complete",
      "round": 2,
      "duration": 720,
      "timeElapsed": 627.3809999999974,
      "actualTime": {
        "s": "2025-05-28T16:04:38.231+00:00",
        "e": "2025-05-28T19:24:06.991+00:00",
        "invalid": null,
        "isLuxonInterval": true
      },
      "tags": {
        "_type": "Tags",
        "value": []
      }
    },
    {
      "id": "VZQ7m",
      "type": "Break",
      "status": "complete",
      "round": 2,
      "duration": 0,
      "timeElapsed": 1,
      "actualTime": {
        "s": "2025-05-28T16:04:45.244+00:00",
        "e": "2025-05-28T19:24:07.748+00:00",
        "invalid": null,
        "isLuxonInterval": true
      },
      "tags": {
        "_type": "Tags",
        "value": []
      }
    },
    {
      "id": "iFRIY",
      "type": "Individual Phase",
      "status": "complete",
      "round": 2,
      "duration": 600,
      "timeElapsed": 31.015000000000004,
      "actualTime": {
        "s": "2025-05-28T19:20:31.073+00:00",
        "e": "2025-05-28T19:20:33.405+00:00",
        "invalid": null,
        "isLuxonInterval": true
      },
      "tags": {
        "_type": "Tags",
        "value": []
      }
    },
    {
      "id": "vS8v2",
      "type": "Universal Phase",
      "status": "complete",
      "round": 3,
      "duration": 240,
      "timeElapsed": 1,
      "actualTime": {
        "s": "2025-05-10T22:07:51.603+00:00",
        "e": "2025-05-28T19:24:09.602+00:00",
        "invalid": null,
        "isLuxonInterval": true
      },
      "tags": {
        "_type": "Tags",
        "value": []
      }
    },
    {
      "id": "MFyrT",
      "type": "Societal Phase",
      "status": "complete",
      "round": 3,
      "duration": 600,
      "timeElapsed": 477.31299999999766,
      "actualTime": {
        "s": "2025-04-20T19:28:15.501+00:00",
        "e": "2025-05-28T20:14:54.006+00:00",
        "invalid": null,
        "isLuxonInterval": true
      },
      "tags": {
        "_type": "Tags",
        "value": []
      }
    },
    {
      "id": "dr96n",
      "type": "Galactic Phase",
      "status": "paused",
      "round": 3,
      "duration": 720,
      "timeElapsed": 16753.31400000192,
      "actualTime": {
        "s": "2025-05-28T15:36:19.218+00:00",
        "e": "2025-05-28T15:48:19.218+00:00",
        "invalid": null,
        "isLuxonInterval": true
      },
      "tags": {
        "_type": "Tags",
        "value": []
      }
    },
    {
      "id": "tJXlr",
      "type": "Universal Phase",
      "status": "playing",
      "round": 4,
      "duration": 240,
      "timeElapsed": 23496.98000000262,
      "actualTime": {
        "s": "2025-05-28T16:33:10.602+00:00",
        "e": "2025-05-28T16:37:10.602+00:00",
        "invalid": null,
        "isLuxonInterval": true
      },
      "tags": {
        "_type": "Tags",
        "value": []
      }
    },
    {
      "id": "mBIUo",
      "type": "Societal Phase",
      "status": "idle",
      "round": 4,
      "duration": 600,
      "timeElapsed": 1900.2769999999953,
      "actualTime": {
        "s": "2025-04-16T22:14:26.371+00:00",
        "e": "2025-05-26T00:07:05.892+00:00",
        "invalid": null,
        "isLuxonInterval": true
      },
      "tags": {
        "_type": "Tags",
        "value": []
      }
    },
    {
      "id": "KnY3K",
      "type": "Galactic Phase",
      "status": "idle",
      "round": 4,
      "duration": 720,
      "timeElapsed": 676.124999999999,
      "actualTime": {
        "s": "2025-05-26T00:06:55.382+00:00",
        "e": "2025-05-26T00:06:59.241+00:00",
        "invalid": null,
        "isLuxonInterval": true
      },
      "tags": {
        "_type": "Tags",
        "value": []
      }
    },
    {
      "id": "Oa_Yg",
      "type": "Break",
      "status": "idle",
      "round": 4,
      "duration": 600,
      "timeElapsed": 0,
      "actualTime": {
        "s": "2025-05-17T12:14:53.780+00:00",
        "e": "2025-05-17T12:14:53.780+00:00",
        "invalid": null,
        "isLuxonInterval": true
      },
      "tags": {
        "_type": "Tags",
        "value": []
      }
    },
    {
      "id": "vKnt4",
      "type": "Universal Phase",
      "status": "idle",
      "round": 5,
      "duration": 240,
      "timeElapsed": 0,
      "actualTime": {
        "s": "2025-05-10T03:53:00.133+00:00",
        "e": "2025-05-10T03:53:00.133+00:00",
        "invalid": null,
        "isLuxonInterval": true
      },
      "tags": {
        "_type": "Tags",
        "value": []
      }
    },
    {
      "id": "sJnY3",
      "type": "Societal Phase",
      "status": "idle",
      "round": 5,
      "duration": 600,
      "timeElapsed": 0,
      "actualTime": {
        "s": "2025-05-10T03:53:00.133+00:00",
        "e": "2025-05-10T03:53:00.133+00:00",
        "invalid": null,
        "isLuxonInterval": true
      },
      "tags": {
        "_type": "Tags",
        "value": []
      }
    },
    {
      "id": "C7lmW",
      "type": "Galactic Phase",
      "status": "idle",
      "round": 5,
      "duration": 720,
      "timeElapsed": 0,
      "actualTime": {
        "s": "2025-05-10T03:53:00.133+00:00",
        "e": "2025-05-10T03:53:00.133+00:00",
        "invalid": null,
        "isLuxonInterval": true
      },
      "tags": {
        "_type": "Tags",
        "value": []
      }
    },
    {
      "id": "uf9xF",
      "type": "Universal Phase",
      "status": "idle",
      "round": 6,
      "duration": 240,
      "timeElapsed": 0,
      "actualTime": {
        "s": "2025-05-10T13:19:08.740+00:00",
        "e": "2025-05-10T13:19:08.740+00:00",
        "invalid": null,
        "isLuxonInterval": true
      },
      "tags": {
        "_type": "Tags",
        "value": []
      }
    },
    {
      "id": "ebgeJ",
      "type": "Societal Phase",
      "status": "idle",
      "round": 6,
      "duration": 600,
      "timeElapsed": 0,
      "actualTime": {
        "s": "2025-05-10T13:27:26.238+00:00",
        "e": "2025-05-10T13:27:26.238+00:00",
        "invalid": null,
        "isLuxonInterval": true
      },
      "tags": {
        "_type": "Tags",
        "value": []
      }
    },
    {
      "id": "eTVTw",
      "type": "Galactic Phase",
      "status": "idle",
      "round": 6,
      "duration": 720,
      "timeElapsed": 0,
      "actualTime": {
        "s": "2025-05-12T21:35:21.813+00:00",
        "e": "2025-05-12T21:35:21.813+00:00",
        "invalid": null,
        "isLuxonInterval": true
      },
      "tags": {
        "_type": "Tags",
        "value": []
      }
    },
    {
      "id": "lyb7N",
      "type": "Generational Phase",
      "status": "idle",
      "round": 6,
      "duration": 900,
      "timeElapsed": 0,
      "actualTime": {
        "s": "2025-05-10T15:52:59.017+00:00",
        "e": "2025-05-10T15:52:59.017+00:00",
        "invalid": null,
        "isLuxonInterval": true
      },
      "tags": {
        "_type": "Tags",
        "value": []
      }
    },
    {
      "id": "YTkJJ",
      "type": "Conclusion",
      "status": "idle",
      "round": 6,
      "duration": 600,
      "timeElapsed": 0,
      "actualTime": {
        "s": "2025-05-10T16:06:55.646+00:00",
        "e": "2025-05-10T16:06:55.646+00:00",
        "invalid": null,
        "isLuxonInterval": true
      },
      "tags": {
        "_type": "Tags",
        "value": []
      }
    }
  ],
  "players": [],
  "resources": [
    {
      "id": "Ridpo",
      "communityId": "o7kHM",
      "name": "dogs",
      "tags": {
        "_type": "Tags",
        "value": []
      }
    },
    {
      "id": "HOzO6",
      "communityId": "LiQVN",
      "name": "feral cats",
      "tags": {
        "_type": "Tags",
        "value": [
          "vital",
          "exhausted"
        ]
      }
    },
    {
      "id": "FADd2",
      "communityId": "NVQbL",
      "name": "lillypadz",
      "tags": {
        "_type": "Tags",
        "value": []
      }
    },
    {
      "id": "QvweM",
      "communityId": "cV-Kn",
      "name": "arg",
      "tags": {
        "_type": "Tags",
        "value": []
      }
    },
    {
      "id": "YaD-S",
      "communityId": "kATHn",
      "name": "shtrhstr",
      "tags": {
        "_type": "Tags",
        "value": []
      }
    },
    {
      "id": "JvqsG",
      "communityId": "Qw0Xm",
      "name": "righteous anger",
      "tags": {
        "_type": "Tags",
        "value": [
          "exhausted"
        ]
      }
    },
    {
      "id": "arNw1",
      "communityId": "B95dD",
      "name": "afergre",
      "tags": {
        "_type": "Tags",
        "value": []
      }
    },
    {
      "id": "BqPmG",
      "communityId": "kATHn",
      "name": "asdfaergre",
      "tags": {
        "_type": "Tags",
        "value": []
      }
    },
    {
      "id": "oxn07",
      "communityId": "lHvo5",
      "name": "blergh",
      "tags": {
        "_type": "Tags",
        "value": [
          "exhausted"
        ]
      }
    },
    {
      "id": "zj1sr",
      "communityId": "G_9_r",
      "name": "hey now",
      "tags": {
        "_type": "Tags",
        "value": [
          "exhausted"
        ]
      }
    },
    {
      "id": "h463E",
      "communityId": "FRomU",
      "name": "new",
      "tags": {
        "_type": "Tags",
        "value": []
      }
    },
    {
      "id": "wRedp",
      "communityId": "ssnLF",
      "name": "adfasd",
      "tags": {
        "_type": "Tags",
        "value": [
          "exhausted"
        ]
      }
    },
    {
      "id": "Mqfth",
      "communityId": "lHvo5",
      "name": "bytes",
      "tags": {
        "_type": "Tags",
        "value": [
          "exhausted"
        ]
      }
    },
    {
      "id": "psJiM",
      "communityId": "NzLOs",
      "name": "urk87kru",
      "tags": {
        "_type": "Tags",
        "value": [
          "exhausted"
        ]
      }
    },
    {
      "id": "KB9VT",
      "communityId": "jaCtF",
      "name": "scum",
      "tags": {
        "_type": "Tags",
        "value": []
      }
    },
    {
      "id": "vi3Gq",
      "communityId": "R9tmF",
      "name": "wgrtgrtgw",
      "tags": {
        "_type": "Tags",
        "value": []
      }
    },
    {
      "id": "AwCCh",
      "communityId": "UDMgC",
      "name": "gwgwrtgwrt",
      "tags": {
        "_type": "Tags",
        "value": [
          "exhausted"
        ]
      }
    },
    {
      "id": "KE7q4",
      "communityId": "PIBFt",
      "name": "toads",
      "tags": {
        "_type": "Tags",
        "value": [
          "exhausted"
        ]
      }
    }
  ],
  "societies": [
    {
      "id": "et0k8",
      "name": "Frog house",
      "archetype": "the faithful",
      "color": "color-deep-orange",
      "tags": {
        "_type": "Tags",
        "value": []
      },
      "roundData": [
        {
          "round": {
            "round": 3,
            "societyId": "et0k8"
          },
          "leadershipOverrides": {}
        },
        {
          "round": {
            "round": "round=",
            "societyId": "et0k8"
          },
          "emissaryCommunityId": "cV-Kn",
          "leadershipOverrides": {}
        },
        {
          "round": {
            "round": 3,
            "societyId": "et0k8"
          },
          "leadershipOverrides": {}
        },
        {
          "round": {
            "round": "round=",
            "societyId": "et0k8"
          },
          "emissaryCommunityId": "B95dD",
          "leadershipOverrides": {}
        },
        {
          "round": 0,
          "societyId": "et0k8",
          "leadershipOverrides": {},
          "ambassadorsSent": []
        },
        {
          "round": 1,
          "societyId": "et0k8",
          "leadershipOverrides": {},
          "ambassadorsSent": []
        },
        {
          "round": 2,
          "societyId": "et0k8",
          "leadershipOverrides": {},
          "ambassadorsSent": []
        },
        {
          "round": 3,
          "societyId": "et0k8",
          "emissaryCommunityId": "",
          "leadershipOverrides": {}
        }
      ]
    },
    {
      "id": "V9xbw",
      "name": "Toad Shack",
      "archetype": "the aesthetic",
      "color": "color-light-blue",
      "tags": {
        "_type": "Tags",
        "value": []
      },
      "roundData": [
        {
          "round": 0,
          "societyId": "V9xbw",
          "leadershipOverrides": {},
          "ambassadorsSent": []
        },
        {
          "round": 1,
          "societyId": "V9xbw",
          "leadershipOverrides": {},
          "ambassadorsSent": []
        },
        {
          "round": 2,
          "societyId": "V9xbw",
          "leadershipOverrides": {},
          "ambassadorsSent": []
        },
        {
          "round": 3,
          "societyId": "V9xbw",
          "leadershipOverrides": {},
          "emissaryCommunityId": "lHvo5"
        }
      ]
    },
    {
      "id": "Feay0",
      "name": "Beetle Junkies",
      "archetype": "the mighty",
      "color": "color-deep-purple",
      "tags": {
        "_type": "Tags",
        "value": []
      },
      "roundData": [
        {
          "round": 0,
          "societyId": "Feay0",
          "leadershipOverrides": {},
          "ambassadorsSent": []
        },
        {
          "round": 1,
          "societyId": "Feay0",
          "leadershipOverrides": {},
          "ambassadorsSent": []
        },
        {
          "round": 2,
          "societyId": "Feay0",
          "leadershipOverrides": {},
          "ambassadorsSent": [],
          "emissaryCommunityId": "NzLOs"
        },
        {
          "round": 3,
          "societyId": "Feay0",
          "leadershipOverrides": {},
          "emissaryCommunityId": "ssnLF"
        }
      ]
    },
    {
      "id": "e-JcG",
      "name": "Better Burritos",
      "archetype": "the intrepid",
      "color": "color-river-stone",
      "tags": {
        "_type": "Tags",
        "value": []
      },
      "roundData": [
        {
          "round": 0,
          "societyId": "e-JcG",
          "leadershipOverrides": {},
          "ambassadorsSent": []
        },
        {
          "round": 1,
          "societyId": "e-JcG",
          "leadershipOverrides": {},
          "ambassadorsSent": []
        },
        {
          "round": 2,
          "societyId": "e-JcG",
          "leadershipOverrides": {},
          "ambassadorsSent": []
        },
        {
          "round": 3,
          "societyId": "e-JcG",
          "leadershipOverrides": {},
          "emissaryCommunityId": ""
        }
      ]
    },
    {
      "id": "yXHVO",
      "name": "Musical Chairs",
      "archetype": "the enterprise",
      "color": "color-canary-diamond",
      "tags": {
        "_type": "Tags",
        "value": []
      },
      "roundData": [
        {
          "round": 0,
          "societyId": "yXHVO",
          "leadershipOverrides": {},
          "ambassadorsSent": []
        },
        {
          "round": 1,
          "societyId": "yXHVO",
          "leadershipOverrides": {},
          "ambassadorsSent": []
        },
        {
          "round": 2,
          "societyId": "yXHVO",
          "leadershipOverrides": {},
          "ambassadorsSent": [],
          "emissaryCommunityId": "jaCtF"
        },
        {
          "round": 3,
          "societyId": "yXHVO",
          "leadershipOverrides": {}
        }
      ]
    }
  ],
  "documentIds": [
    "Wt6ry",
    "ZWFCD",
    "Ka3FF"
  ],
  "links": {
    "discord": "discord://-/channels/1063250197993492480/1063254140341473350"
  },
  "records": [
    {
      "id": "yxo_p",
      "timestamp": "2025-04-16T22:12:27.348+00:00",
      "type": "PhaseStarted",
      "description": "Round 0: Setup Phase",
      "value": "2025-04-16T22:12:27.348+00:00"
    },
    {
      "id": "hi0Ny",
      "timestamp": "2025-04-16T22:12:30.475+00:00",
      "type": "PhaseEnded",
      "description": "Round 0: Setup Phase",
      "value": "2025-04-16T22:12:30.475+00:00"
    },
    {
      "id": "NKic2",
      "timestamp": "2025-04-16T22:12:30.475+00:00",
      "type": "PhaseDuration",
      "description": "Round 0: Setup Phase",
      "value": 0.052116666666666665
    },
    {
      "id": "h9t6T",
      "timestamp": "2025-04-16T22:12:30.475+00:00",
      "type": "SocietyActionsTaken",
      "description": "First Society",
      "value": 0
    },
    {
      "id": "A5XPR",
      "timestamp": "2025-04-16T22:12:30.475+00:00",
      "type": "SocietyActionsTaken",
      "description": "Second Society",
      "value": 0
    },
    {
      "id": "CQU3S",
      "timestamp": "2025-04-16T22:12:30.475+00:00",
      "type": "SocietyActionsTaken",
      "description": "Third Society",
      "value": 0
    },
    {
      "id": "lH-YA",
      "timestamp": "2025-04-16T22:12:31.858+00:00",
      "type": "PhaseStarted",
      "description": "Round 1: Universal Phase",
      "value": "2025-04-16T22:12:31.858+00:00"
    },
    {
      "id": "BMmxG",
      "timestamp": "2025-04-16T22:12:50.298+00:00",
      "type": "PhaseEnded",
      "description": "Round 1: Universal Phase",
      "value": "2025-04-16T22:12:50.298+00:00"
    },
    {
      "id": "j18Cc",
      "timestamp": "2025-04-16T22:12:50.298+00:00",
      "type": "PhaseDuration",
      "description": "Round 1: Universal Phase",
      "value": 0.30733333333333335
    },
    {
      "id": "j3tYz",
      "timestamp": "2025-04-16T22:12:53.129+00:00",
      "type": "PhaseStarted",
      "description": "Round 1: Societal Phase",
      "value": "2025-04-16T22:12:53.129+00:00"
    },
    {
      "id": "YVjR3",
      "timestamp": "2025-04-16T22:14:26.371+00:00",
      "type": "PhaseStarted",
      "description": "Round 1: Societal Phase",
      "value": "2025-04-16T22:14:26.371+00:00"
    },
    {
      "id": "Mg5AK",
      "timestamp": "2025-04-18T00:39:20.763+00:00",
      "type": "PhaseStarted",
      "description": "Round 1: Galactic Phase",
      "value": "2025-04-18T00:39:20.763+00:00"
    },
    {
      "id": "iZ-xi",
      "timestamp": "2025-04-18T00:39:32.348+00:00",
      "type": "PhaseEnded",
      "description": "Round 1: Galactic Phase",
      "value": "2025-04-18T00:39:32.348+00:00"
    },
    {
      "id": "Q0RV1",
      "timestamp": "2025-04-18T00:39:32.350+00:00",
      "type": "PhaseDuration",
      "description": "Round 1: Galactic Phase",
      "value": 0.19308333333333333
    },
    {
      "id": "KNugS",
      "timestamp": "2025-04-18T00:39:39.028+00:00",
      "type": "SocietyActionsTaken",
      "description": "First Society",
      "value": 0
    },
    {
      "id": "eGQkJ",
      "timestamp": "2025-04-18T00:39:39.028+00:00",
      "type": "SocietyActionsTaken",
      "description": "Second Society",
      "value": 0
    },
    {
      "id": "cc0e5",
      "timestamp": "2025-04-18T00:39:39.028+00:00",
      "type": "SocietyActionsTaken",
      "description": "Third Society",
      "value": 0
    },
    {
      "id": "XDoEZ",
      "timestamp": "2025-04-18T01:29:15.120+00:00",
      "type": "PhaseStarted",
      "description": "Round 2: Universal Phase",
      "value": "2025-04-18T01:29:15.120+00:00"
    },
    {
      "id": "tOQ0w",
      "timestamp": "2025-04-18T01:29:17.416+00:00",
      "type": "PhaseEnded",
      "description": "Round 2: Universal Phase",
      "value": "2025-04-18T01:29:17.416+00:00"
    },
    {
      "id": "uGaDT",
      "timestamp": "2025-04-18T01:29:17.416+00:00",
      "type": "PhaseDuration",
      "description": "Round 2: Universal Phase",
      "value": 0.03825
    },
    {
      "id": "Ljzj7",
      "timestamp": "2025-04-18T01:30:54.802+00:00",
      "type": "PhaseStarted",
      "description": "Round 1: Individual Phase",
      "value": "2025-04-18T01:30:54.802+00:00"
    },
    {
      "id": "RKVUU",
      "timestamp": "2025-04-18T01:32:04.337+00:00",
      "type": "PhaseStarted",
      "description": "Round 1: Galactic Phase",
      "value": "2025-04-18T01:32:04.337+00:00"
    },
    {
      "id": "y7T6T",
      "timestamp": "2025-04-18T01:43:06.624+00:00",
      "type": "PhaseEnded",
      "description": "Round 1: Galactic Phase",
      "value": "2025-04-18T01:43:06.624+00:00"
    },
    {
      "id": "nFBDp",
      "timestamp": "2025-04-18T01:43:06.664+00:00",
      "type": "PhaseDuration",
      "description": "Round 1: Galactic Phase",
      "value": 11.038116666666667
    },
    {
      "id": "U7lGn",
      "timestamp": "2025-04-18T01:43:40.834+00:00",
      "type": "ResourceCreated",
      "value": "dogs"
    },
    {
      "id": "HWpb_",
      "timestamp": "2025-04-18T01:43:48.543+00:00",
      "type": "ResourceCreated",
      "value": "cats"
    },
    {
      "id": "dnpZ1",
      "timestamp": "2025-04-20T19:16:14.219+00:00",
      "type": "PhaseStarted",
      "description": "Round 1: Individual Phase",
      "value": "2025-04-20T19:16:14.219+00:00"
    },
    {
      "id": "ZVZRu",
      "timestamp": "2025-04-20T19:16:15.964+00:00",
      "type": "PhaseEnded",
      "description": "Round 1: Individual Phase",
      "value": "2025-04-20T19:16:15.964+00:00"
    },
    {
      "id": "X2bcV",
      "timestamp": "2025-04-20T19:16:15.965+00:00",
      "type": "PhaseDuration",
      "description": "Round 1: Individual Phase",
      "value": 0.029083333333333333
    },
    {
      "id": "cYUzG",
      "timestamp": "2025-04-20T19:16:15.965+00:00",
      "type": "SocietyActionsTaken",
      "description": "First Society",
      "value": 1
    },
    {
      "id": "iU1qS",
      "timestamp": "2025-04-20T19:16:15.965+00:00",
      "type": "ActionResources",
      "description": "First Society used dogs,cats to take action.",
      "value": 2
    },
    {
      "id": "rAdV-",
      "timestamp": "2025-04-20T19:16:15.965+00:00",
      "type": "SocietyActionsTaken",
      "description": "Second Society",
      "value": 0
    },
    {
      "id": "h36_Q",
      "timestamp": "2025-04-20T19:16:15.965+00:00",
      "type": "SocietyActionsTaken",
      "description": "Third Society",
      "value": 0
    },
    {
      "id": "fWyPf",
      "timestamp": "2025-04-20T19:17:34.606+00:00",
      "type": "PhaseStarted",
      "description": "Round 2: Universal Phase",
      "value": "2025-04-20T19:17:34.606+00:00"
    },
    {
      "id": "OvfFf",
      "timestamp": "2025-04-20T19:27:28.862+00:00",
      "type": "ResourceCreated",
      "value": "lillypadz"
    },
    {
      "id": "tRua8",
      "timestamp": "2025-04-20T19:28:02.211+00:00",
      "type": "PhaseStarted",
      "description": "Round 2: Societal Phase",
      "value": "2025-04-20T19:28:02.211+00:00"
    },
    {
      "id": "T3wKa",
      "timestamp": "2025-04-20T19:28:15.502+00:00",
      "type": "PhaseStarted",
      "description": "Round 2: Societal Phase",
      "value": "2025-04-20T19:28:15.502+00:00"
    },
    {
      "id": "X-PS4",
      "timestamp": "2025-05-10T17:48:47.649+00:00",
      "type": "PhaseEnded",
      "description": "Round 2: Societal Phase",
      "value": "2025-05-10T17:48:47.649+00:00"
    },
    {
      "id": "gPTcN",
      "timestamp": "2025-05-10T17:48:47.650+00:00",
      "type": "PhaseDuration",
      "description": "Round 2: Societal Phase",
      "value": 28700.5358
    },
    {
      "id": "VOG5w",
      "timestamp": "2025-05-10T17:51:25.097+00:00",
      "type": "PhaseStarted",
      "description": "Round 2: Break",
      "value": "2025-05-10T17:51:25.097+00:00"
    },
    {
      "id": "Cm2RO",
      "timestamp": "2025-05-13T23:22:59.827+00:00",
      "type": "PhaseStarted",
      "description": "Round 1: Universal Phase",
      "value": "2025-05-13T23:22:59.827+00:00"
    },
    {
      "id": "frvLq",
      "timestamp": "2025-05-13T23:51:02.030+00:00",
      "type": "PhaseStarted",
      "description": "Round 1: Universal Phase",
      "value": "2025-05-13T23:51:02.030+00:00"
    },
    {
      "id": "odvS7",
      "timestamp": "2025-05-14T00:13:22.381+00:00",
      "type": "ResourceCreated",
      "value": "arg"
    },
    {
      "id": "Ujxmx",
      "timestamp": "2025-05-14T00:13:24.049+00:00",
      "type": "ResourceCreated",
      "value": "shtrhstr"
    },
    {
      "id": "viPoR",
      "timestamp": "2025-05-14T00:13:25.870+00:00",
      "type": "ResourceCreated",
      "value": "aerger"
    },
    {
      "id": "DbgzC",
      "timestamp": "2025-05-14T00:13:31.874+00:00",
      "type": "ResourceCreated",
      "value": "afergre"
    },
    {
      "id": "dSA2z",
      "timestamp": "2025-05-14T00:13:35.472+00:00",
      "type": "ResourceCreated",
      "value": "asdfaergre"
    },
    {
      "id": "dOsbG",
      "timestamp": "2025-05-16T15:29:27.130+00:00",
      "type": "SocietyActionsTaken",
      "description": "Frog house",
      "value": 1
    },
    {
      "id": "ao5zT",
      "timestamp": "2025-05-16T15:29:27.130+00:00",
      "type": "ActionResources",
      "description": "Frog house used cats to take action.",
      "value": 1
    },
    {
      "id": "L-XVg",
      "timestamp": "2025-05-16T15:29:27.130+00:00",
      "type": "SocietyActionsTaken",
      "description": "Toad Shack",
      "value": 0
    },
    {
      "id": "hS3xD",
      "timestamp": "2025-05-16T15:29:27.130+00:00",
      "type": "SocietyActionsTaken",
      "description": "Beetle Junkies",
      "value": 0
    },
    {
      "id": "hv8JI",
      "timestamp": "2025-05-16T15:29:27.131+00:00",
      "type": "SocietyActionsTaken",
      "description": "Better Burritos",
      "value": 0
    },
    {
      "id": "DxTSz",
      "timestamp": "2025-05-16T15:29:27.131+00:00",
      "type": "SocietyActionsTaken",
      "description": "Musical Chairs",
      "value": 0
    },
    {
      "id": "e9NXZ",
      "timestamp": "2025-05-16T15:29:29.374+00:00",
      "type": "SocietyActionsTaken",
      "description": "Frog house",
      "value": 1
    },
    {
      "id": "NRtTC",
      "timestamp": "2025-05-16T15:29:29.374+00:00",
      "type": "ActionResources",
      "description": "Frog house used cats to take action.",
      "value": 1
    },
    {
      "id": "bVYCu",
      "timestamp": "2025-05-16T15:29:29.374+00:00",
      "type": "SocietyActionsTaken",
      "description": "Toad Shack",
      "value": 0
    },
    {
      "id": "Fa3De",
      "timestamp": "2025-05-16T15:29:29.374+00:00",
      "type": "SocietyActionsTaken",
      "description": "Beetle Junkies",
      "value": 0
    },
    {
      "id": "uDf-k",
      "timestamp": "2025-05-16T15:29:29.375+00:00",
      "type": "SocietyActionsTaken",
      "description": "Better Burritos",
      "value": 0
    },
    {
      "id": "fgkSU",
      "timestamp": "2025-05-16T15:29:29.375+00:00",
      "type": "SocietyActionsTaken",
      "description": "Musical Chairs",
      "value": 0
    },
    {
      "id": "rikTC",
      "timestamp": "2025-05-16T15:29:56.330+00:00",
      "type": "SocietyActionsTaken",
      "description": "Frog house",
      "value": 0
    },
    {
      "id": "Mfo8j",
      "timestamp": "2025-05-16T15:29:56.330+00:00",
      "type": "SocietyActionsTaken",
      "description": "Toad Shack",
      "value": 0
    },
    {
      "id": "N0NiZ",
      "timestamp": "2025-05-16T15:29:56.330+00:00",
      "type": "SocietyActionsTaken",
      "description": "Beetle Junkies",
      "value": 0
    },
    {
      "id": "XpNpK",
      "timestamp": "2025-05-16T15:29:56.330+00:00",
      "type": "SocietyActionsTaken",
      "description": "Better Burritos",
      "value": 0
    },
    {
      "id": "M5dJk",
      "timestamp": "2025-05-16T15:29:56.331+00:00",
      "type": "SocietyActionsTaken",
      "description": "Musical Chairs",
      "value": 0
    },
    {
      "id": "LsnD5",
      "timestamp": "2025-05-17T12:14:33.001+00:00",
      "type": "SocietyActionsTaken",
      "description": "Frog house",
      "value": 1
    },
    {
      "id": "dv579",
      "timestamp": "2025-05-17T12:14:33.002+00:00",
      "type": "ActionResources",
      "description": "Frog house used cats to take action.",
      "value": 1
    },
    {
      "id": "DrttI",
      "timestamp": "2025-05-17T12:14:33.002+00:00",
      "type": "SocietyActionsTaken",
      "description": "Toad Shack",
      "value": 0
    },
    {
      "id": "Z0NE0",
      "timestamp": "2025-05-17T12:14:33.002+00:00",
      "type": "SocietyActionsTaken",
      "description": "Beetle Junkies",
      "value": 0
    },
    {
      "id": "EaaPW",
      "timestamp": "2025-05-17T12:14:33.002+00:00",
      "type": "SocietyActionsTaken",
      "description": "Better Burritos",
      "value": 0
    },
    {
      "id": "E_TIE",
      "timestamp": "2025-05-17T12:14:33.002+00:00",
      "type": "SocietyActionsTaken",
      "description": "Musical Chairs",
      "value": 0
    },
    {
      "id": "uYlbH",
      "timestamp": "2025-05-17T12:14:34.656+00:00",
      "type": "SocietyActionsTaken",
      "description": "Frog house",
      "value": 1
    },
    {
      "id": "t2NZC",
      "timestamp": "2025-05-17T12:14:34.656+00:00",
      "type": "ActionResources",
      "description": "Frog house used cats to take action.",
      "value": 1
    },
    {
      "id": "eKqYR",
      "timestamp": "2025-05-17T12:14:34.656+00:00",
      "type": "SocietyActionsTaken",
      "description": "Toad Shack",
      "value": 0
    },
    {
      "id": "dOw6Z",
      "timestamp": "2025-05-17T12:14:34.656+00:00",
      "type": "SocietyActionsTaken",
      "description": "Beetle Junkies",
      "value": 0
    },
    {
      "id": "bQnt0",
      "timestamp": "2025-05-17T12:14:34.656+00:00",
      "type": "SocietyActionsTaken",
      "description": "Better Burritos",
      "value": 0
    },
    {
      "id": "xGj3f",
      "timestamp": "2025-05-17T12:14:34.656+00:00",
      "type": "SocietyActionsTaken",
      "description": "Musical Chairs",
      "value": 0
    },
    {
      "id": "BJLdR",
      "timestamp": "2025-05-17T12:14:35.842+00:00",
      "type": "SocietyActionsTaken",
      "description": "Frog house",
      "value": 0
    },
    {
      "id": "Un65i",
      "timestamp": "2025-05-17T12:14:35.842+00:00",
      "type": "SocietyActionsTaken",
      "description": "Toad Shack",
      "value": 0
    },
    {
      "id": "v_EHf",
      "timestamp": "2025-05-17T12:14:35.842+00:00",
      "type": "SocietyActionsTaken",
      "description": "Beetle Junkies",
      "value": 0
    },
    {
      "id": "ODsAh",
      "timestamp": "2025-05-17T12:14:35.842+00:00",
      "type": "SocietyActionsTaken",
      "description": "Better Burritos",
      "value": 0
    },
    {
      "id": "XRFNw",
      "timestamp": "2025-05-17T12:14:35.842+00:00",
      "type": "SocietyActionsTaken",
      "description": "Musical Chairs",
      "value": 0
    },
    {
      "id": "km4qV",
      "timestamp": "2025-05-17T12:17:07.992+00:00",
      "type": "SocietyActionsTaken",
      "description": "Frog house",
      "value": 1
    },
    {
      "id": "pOJA8",
      "timestamp": "2025-05-17T12:17:07.992+00:00",
      "type": "ActionResources",
      "description": "Frog house used cats to take action.",
      "value": 1
    },
    {
      "id": "jki2B",
      "timestamp": "2025-05-17T12:17:07.992+00:00",
      "type": "SocietyActionsTaken",
      "description": "Toad Shack",
      "value": 0
    },
    {
      "id": "ngpvu",
      "timestamp": "2025-05-17T12:17:07.992+00:00",
      "type": "SocietyActionsTaken",
      "description": "Beetle Junkies",
      "value": 0
    },
    {
      "id": "MbM5z",
      "timestamp": "2025-05-17T12:17:07.992+00:00",
      "type": "SocietyActionsTaken",
      "description": "Better Burritos",
      "value": 0
    },
    {
      "id": "Orccn",
      "timestamp": "2025-05-17T12:17:07.992+00:00",
      "type": "SocietyActionsTaken",
      "description": "Musical Chairs",
      "value": 0
    },
    {
      "id": "QhinK",
      "timestamp": "2025-05-17T12:52:32.197+00:00",
      "type": "ResourceCreated",
      "value": "blergh"
    },
    {
      "id": "BGlIO",
      "timestamp": "2025-05-18T13:02:00.820+00:00",
      "type": "ResourceCreated",
      "value": "hey now"
    },
    {
      "id": "plxGt",
      "timestamp": "2025-05-18T13:07:04.561+00:00",
      "type": "ResourceCreated",
      "value": "a new resource"
    },
    {
      "id": "gS5no",
      "timestamp": "2025-05-18T13:09:15.068+00:00",
      "type": "ResourceCreated",
      "value": "new"
    },
    {
      "id": "XIBeR",
      "timestamp": "2025-05-18T13:10:08.012+00:00",
      "type": "ResourceCreated",
      "value": "adfasd"
    },
    {
      "id": "KaLi0",
      "timestamp": "2025-05-18T13:10:26.040+00:00",
      "type": "ResourceCreated",
      "value": "agr"
    },
    {
      "id": "aNm9y",
      "timestamp": "2025-05-18T13:10:58.488+00:00",
      "type": "ResourceCreated",
      "value": "etyjetyj"
    },
    {
      "id": "gdXCC",
      "timestamp": "2025-05-18T13:11:33.433+00:00",
      "type": "ResourceCreated",
      "value": "bytes"
    },
    {
      "id": "OXey5",
      "timestamp": "2025-05-18T13:11:42.357+00:00",
      "type": "ResourceCreated",
      "value": "urk87kru"
    },
    {
      "id": "CDe4h",
      "timestamp": "2025-05-18T13:23:49.018+00:00",
      "type": "ResourceCreated",
      "value": "scum"
    },
    {
      "id": "Uu1vM",
      "timestamp": "2025-05-18T13:45:42.926+00:00",
      "type": "SocietyActionsTaken",
      "description": "Frog house",
      "value": 1
    },
    {
      "id": "bjrYR",
      "timestamp": "2025-05-18T13:45:42.927+00:00",
      "type": "ActionResources",
      "description": "Frog house used cats to take action.",
      "value": 1
    },
    {
      "id": "s1DZB",
      "timestamp": "2025-05-18T13:45:42.927+00:00",
      "type": "SocietyActionsTaken",
      "description": "Toad Shack",
      "value": 0
    },
    {
      "id": "D0KDI",
      "timestamp": "2025-05-18T13:45:42.927+00:00",
      "type": "SocietyActionsTaken",
      "description": "Beetle Junkies",
      "value": 1
    },
    {
      "id": "zOkxo",
      "timestamp": "2025-05-18T13:45:42.927+00:00",
      "type": "ActionResources",
      "description": "Beetle Junkies used blergh to take action.",
      "value": 1
    },
    {
      "id": "QXEgX",
      "timestamp": "2025-05-18T13:45:42.927+00:00",
      "type": "SocietyActionsTaken",
      "description": "Better Burritos",
      "value": 0
    },
    {
      "id": "VkRiu",
      "timestamp": "2025-05-18T13:45:42.927+00:00",
      "type": "SocietyActionsTaken",
      "description": "Musical Chairs",
      "value": 0
    },
    {
      "id": "R6hry",
      "timestamp": "2025-05-18T13:46:32.804+00:00",
      "type": "SocietyActionsTaken",
      "description": "Frog house",
      "value": 1
    },
    {
      "id": "FE-K5",
      "timestamp": "2025-05-18T13:46:32.804+00:00",
      "type": "ActionResources",
      "description": "Frog house used cats to take action.",
      "value": 1
    },
    {
      "id": "jM5oJ",
      "timestamp": "2025-05-18T13:46:32.804+00:00",
      "type": "SocietyActionsTaken",
      "description": "Toad Shack",
      "value": 0
    },
    {
      "id": "ToBho",
      "timestamp": "2025-05-18T13:46:32.804+00:00",
      "type": "SocietyActionsTaken",
      "description": "Beetle Junkies",
      "value": 1
    },
    {
      "id": "w_pkM",
      "timestamp": "2025-05-18T13:46:32.804+00:00",
      "type": "ActionResources",
      "description": "Beetle Junkies used blergh to take action.",
      "value": 1
    },
    {
      "id": "uRX88",
      "timestamp": "2025-05-18T13:46:32.805+00:00",
      "type": "SocietyActionsTaken",
      "description": "Better Burritos",
      "value": 0
    },
    {
      "id": "HQoaN",
      "timestamp": "2025-05-18T13:46:32.805+00:00",
      "type": "SocietyActionsTaken",
      "description": "Musical Chairs",
      "value": 0
    },
    {
      "id": "PijmU",
      "timestamp": "2025-05-18T13:46:34.444+00:00",
      "type": "SocietyActionsTaken",
      "description": "Frog house",
      "value": 1
    },
    {
      "id": "XC2tw",
      "timestamp": "2025-05-18T13:46:34.444+00:00",
      "type": "ActionResources",
      "description": "Frog house used cats to take action.",
      "value": 1
    },
    {
      "id": "thTyL",
      "timestamp": "2025-05-18T13:46:34.444+00:00",
      "type": "SocietyActionsTaken",
      "description": "Toad Shack",
      "value": 0
    },
    {
      "id": "HVgmZ",
      "timestamp": "2025-05-18T13:46:34.444+00:00",
      "type": "SocietyActionsTaken",
      "description": "Beetle Junkies",
      "value": 1
    },
    {
      "id": "h1DcB",
      "timestamp": "2025-05-18T13:46:34.444+00:00",
      "type": "ActionResources",
      "description": "Beetle Junkies used blergh to take action.",
      "value": 1
    },
    {
      "id": "II89K",
      "timestamp": "2025-05-18T13:46:34.444+00:00",
      "type": "SocietyActionsTaken",
      "description": "Better Burritos",
      "value": 0
    },
    {
      "id": "i-Id7",
      "timestamp": "2025-05-18T13:46:34.444+00:00",
      "type": "SocietyActionsTaken",
      "description": "Musical Chairs",
      "value": 0
    },
    {
      "id": "L9Vzo",
      "timestamp": "2025-05-18T13:50:41.197+00:00",
      "type": "SocietyActionsTaken",
      "description": "Frog house",
      "value": 1
    },
    {
      "id": "ZU4Wc",
      "timestamp": "2025-05-18T13:50:41.197+00:00",
      "type": "ActionResources",
      "description": "Frog house used cats to take action.",
      "value": 1
    },
    {
      "id": "L8Q85",
      "timestamp": "2025-05-18T13:50:41.197+00:00",
      "type": "SocietyActionsTaken",
      "description": "Toad Shack",
      "value": 0
    },
    {
      "id": "PgTRt",
      "timestamp": "2025-05-18T13:50:41.197+00:00",
      "type": "SocietyActionsTaken",
      "description": "Beetle Junkies",
      "value": 0
    },
    {
      "id": "oxmBi",
      "timestamp": "2025-05-18T13:50:41.197+00:00",
      "type": "SocietyActionsTaken",
      "description": "Better Burritos",
      "value": 0
    },
    {
      "id": "b9-mm",
      "timestamp": "2025-05-18T13:50:41.197+00:00",
      "type": "SocietyActionsTaken",
      "description": "Musical Chairs",
      "value": 0
    },
    {
      "id": "Z7dvo",
      "timestamp": "2025-05-18T13:50:42.807+00:00",
      "type": "SocietyActionsTaken",
      "description": "Frog house",
      "value": 1
    },
    {
      "id": "HBE22",
      "timestamp": "2025-05-18T13:50:42.807+00:00",
      "type": "ActionResources",
      "description": "Frog house used cats to take action.",
      "value": 1
    },
    {
      "id": "ZvoJn",
      "timestamp": "2025-05-18T13:50:42.807+00:00",
      "type": "SocietyActionsTaken",
      "description": "Toad Shack",
      "value": 0
    },
    {
      "id": "KdFj2",
      "timestamp": "2025-05-18T13:50:42.807+00:00",
      "type": "SocietyActionsTaken",
      "description": "Beetle Junkies",
      "value": 0
    },
    {
      "id": "eAzqC",
      "timestamp": "2025-05-18T13:50:42.807+00:00",
      "type": "SocietyActionsTaken",
      "description": "Better Burritos",
      "value": 0
    },
    {
      "id": "tKn5C",
      "timestamp": "2025-05-18T13:50:42.807+00:00",
      "type": "SocietyActionsTaken",
      "description": "Musical Chairs",
      "value": 0
    },
    {
      "id": "T49TB",
      "timestamp": "2025-05-18T14:03:34.093+00:00",
      "type": "SocietyActionsTaken",
      "description": "Frog house",
      "value": 1
    },
    {
      "id": "X18G6",
      "timestamp": "2025-05-18T14:03:34.093+00:00",
      "type": "ActionResources",
      "description": "Frog house used cats to take action.",
      "value": 1
    },
    {
      "id": "V9uZu",
      "timestamp": "2025-05-18T14:03:34.094+00:00",
      "type": "SocietyActionsTaken",
      "description": "Toad Shack",
      "value": 0
    },
    {
      "id": "KPSXN",
      "timestamp": "2025-05-18T14:03:34.094+00:00",
      "type": "SocietyActionsTaken",
      "description": "Beetle Junkies",
      "value": 0
    },
    {
      "id": "nkFeW",
      "timestamp": "2025-05-18T14:03:34.094+00:00",
      "type": "SocietyActionsTaken",
      "description": "Better Burritos",
      "value": 0
    },
    {
      "id": "EvR9u",
      "timestamp": "2025-05-18T14:03:34.094+00:00",
      "type": "SocietyActionsTaken",
      "description": "Musical Chairs",
      "value": 0
    },
    {
      "id": "vAmxL",
      "timestamp": "2025-05-18T14:03:51.647+00:00",
      "type": "PhaseStarted",
      "description": "Round 2: Societal Phase",
      "value": "2025-05-18T14:03:51.647+00:00"
    },
    {
      "id": "iJf0x",
      "timestamp": "2025-05-18T14:03:54.141+00:00",
      "type": "PhaseStarted",
      "description": "Round 2: Societal Phase",
      "value": "2025-05-18T14:03:54.141+00:00"
    },
    {
      "id": "n3j9a",
      "timestamp": "2025-05-18T14:06:27.460+00:00",
      "type": "PhaseStarted",
      "description": "Round 2: Societal Phase",
      "value": "2025-05-18T14:06:27.460+00:00"
    },
    {
      "id": "eM9rH",
      "timestamp": "2025-05-19T20:06:12.475+00:00",
      "type": "PhaseStarted",
      "description": "Round 2: Societal Phase",
      "value": "2025-05-19T20:06:12.474+00:00"
    },
    {
      "id": "Ne8zA",
      "timestamp": "2025-05-19T20:06:55.833+00:00",
      "type": "PhaseStarted",
      "description": "Round 2: Societal Phase",
      "value": "2025-05-19T20:06:55.833+00:00"
    },
    {
      "id": "GtkHj",
      "timestamp": "2025-05-19T22:13:39.960+00:00",
      "type": "PhaseStarted",
      "description": "Round 2: Societal Phase",
      "value": "2025-05-19T22:13:39.960+00:00"
    },
    {
      "id": "UcdA1",
      "timestamp": "2025-05-20T21:09:06.367+00:00",
      "type": "SocietyActionsTaken",
      "description": "Frog house",
      "value": 1
    },
    {
      "id": "OgXhx",
      "timestamp": "2025-05-20T21:09:06.367+00:00",
      "type": "ActionResources",
      "description": "Frog house used feral cats,righteous anger to take action.",
      "value": 2
    },
    {
      "id": "tLBwB",
      "timestamp": "2025-05-20T21:09:06.367+00:00",
      "type": "SocietyActionsTaken",
      "description": "Toad Shack",
      "value": 0
    },
    {
      "id": "n5Idk",
      "timestamp": "2025-05-20T21:09:06.367+00:00",
      "type": "SocietyActionsTaken",
      "description": "Beetle Junkies",
      "value": 2
    },
    {
      "id": "H7-fo",
      "timestamp": "2025-05-20T21:09:06.367+00:00",
      "type": "ActionResources",
      "description": "Beetle Junkies used hey now to take action.",
      "value": 1
    },
    {
      "id": "aQjJE",
      "timestamp": "2025-05-20T21:09:06.367+00:00",
      "type": "ActionResources",
      "description": "Beetle Junkies used hey now,bytes to take action.",
      "value": 2
    },
    {
      "id": "pWEws",
      "timestamp": "2025-05-20T21:09:06.367+00:00",
      "type": "SocietyActionsTaken",
      "description": "Better Burritos",
      "value": 0
    },
    {
      "id": "RBUN9",
      "timestamp": "2025-05-20T21:09:06.367+00:00",
      "type": "SocietyActionsTaken",
      "description": "Musical Chairs",
      "value": 1
    },
    {
      "id": "A6YBd",
      "timestamp": "2025-05-20T21:09:06.368+00:00",
      "type": "ActionResources",
      "description": "Musical Chairs used scum to take action.",
      "value": 1
    },
    {
      "id": "HH1AA",
      "timestamp": "2025-05-20T21:09:08.142+00:00",
      "type": "SocietyActionsTaken",
      "description": "Frog house",
      "value": 1
    },
    {
      "id": "x-iyO",
      "timestamp": "2025-05-20T21:09:08.142+00:00",
      "type": "ActionResources",
      "description": "Frog house used feral cats,righteous anger to take action.",
      "value": 2
    },
    {
      "id": "gCQa7",
      "timestamp": "2025-05-20T21:09:08.142+00:00",
      "type": "SocietyActionsTaken",
      "description": "Toad Shack",
      "value": 0
    },
    {
      "id": "w-j4M",
      "timestamp": "2025-05-20T21:09:08.142+00:00",
      "type": "SocietyActionsTaken",
      "description": "Beetle Junkies",
      "value": 2
    },
    {
      "id": "yEGgt",
      "timestamp": "2025-05-20T21:09:08.142+00:00",
      "type": "ActionResources",
      "description": "Beetle Junkies used hey now to take action.",
      "value": 1
    },
    {
      "id": "l_6DY",
      "timestamp": "2025-05-20T21:09:08.142+00:00",
      "type": "ActionResources",
      "description": "Beetle Junkies used hey now,bytes to take action.",
      "value": 2
    },
    {
      "id": "T80aJ",
      "timestamp": "2025-05-20T21:09:08.142+00:00",
      "type": "SocietyActionsTaken",
      "description": "Better Burritos",
      "value": 0
    },
    {
      "id": "BfoY8",
      "timestamp": "2025-05-20T21:09:08.142+00:00",
      "type": "SocietyActionsTaken",
      "description": "Musical Chairs",
      "value": 1
    },
    {
      "id": "XnPA0",
      "timestamp": "2025-05-20T21:09:08.142+00:00",
      "type": "ActionResources",
      "description": "Musical Chairs used scum to take action.",
      "value": 1
    },
    {
      "id": "hsJ19",
      "timestamp": "2025-05-20T21:09:09.071+00:00",
      "type": "SocietyActionsTaken",
      "description": "Frog house",
      "value": 1
    },
    {
      "id": "XZvyM",
      "timestamp": "2025-05-20T21:09:09.071+00:00",
      "type": "ActionResources",
      "description": "Frog house used feral cats,righteous anger to take action.",
      "value": 2
    },
    {
      "id": "GBynl",
      "timestamp": "2025-05-20T21:09:09.071+00:00",
      "type": "SocietyActionsTaken",
      "description": "Toad Shack",
      "value": 0
    },
    {
      "id": "MR0f3",
      "timestamp": "2025-05-20T21:09:09.071+00:00",
      "type": "SocietyActionsTaken",
      "description": "Beetle Junkies",
      "value": 2
    },
    {
      "id": "aZNy_",
      "timestamp": "2025-05-20T21:09:09.071+00:00",
      "type": "ActionResources",
      "description": "Beetle Junkies used hey now to take action.",
      "value": 1
    },
    {
      "id": "AWDR7",
      "timestamp": "2025-05-20T21:09:09.071+00:00",
      "type": "ActionResources",
      "description": "Beetle Junkies used hey now,bytes to take action.",
      "value": 2
    },
    {
      "id": "dJ_I0",
      "timestamp": "2025-05-20T21:09:09.071+00:00",
      "type": "SocietyActionsTaken",
      "description": "Better Burritos",
      "value": 0
    },
    {
      "id": "zHjci",
      "timestamp": "2025-05-20T21:09:09.071+00:00",
      "type": "SocietyActionsTaken",
      "description": "Musical Chairs",
      "value": 1
    },
    {
      "id": "uT-Ig",
      "timestamp": "2025-05-20T21:09:09.071+00:00",
      "type": "ActionResources",
      "description": "Musical Chairs used scum to take action.",
      "value": 1
    },
    {
      "id": "ae9BH",
      "timestamp": "2025-05-20T21:09:16.321+00:00",
      "type": "SocietyActionsTaken",
      "description": "Frog house",
      "value": 1
    },
    {
      "id": "bfaO5",
      "timestamp": "2025-05-20T21:09:16.321+00:00",
      "type": "ActionResources",
      "description": "Frog house used feral cats,righteous anger to take action.",
      "value": 2
    },
    {
      "id": "e9OG2",
      "timestamp": "2025-05-20T21:09:16.321+00:00",
      "type": "SocietyActionsTaken",
      "description": "Toad Shack",
      "value": 0
    },
    {
      "id": "ECl7e",
      "timestamp": "2025-05-20T21:09:16.321+00:00",
      "type": "SocietyActionsTaken",
      "description": "Beetle Junkies",
      "value": 2
    },
    {
      "id": "P3k4m",
      "timestamp": "2025-05-20T21:09:16.321+00:00",
      "type": "ActionResources",
      "description": "Beetle Junkies used hey now to take action.",
      "value": 1
    },
    {
      "id": "gqAab",
      "timestamp": "2025-05-20T21:09:16.321+00:00",
      "type": "ActionResources",
      "description": "Beetle Junkies used hey now,bytes to take action.",
      "value": 2
    },
    {
      "id": "bQtz4",
      "timestamp": "2025-05-20T21:09:16.321+00:00",
      "type": "SocietyActionsTaken",
      "description": "Better Burritos",
      "value": 0
    },
    {
      "id": "uth4a",
      "timestamp": "2025-05-20T21:09:16.321+00:00",
      "type": "SocietyActionsTaken",
      "description": "Musical Chairs",
      "value": 1
    },
    {
      "id": "UO-K_",
      "timestamp": "2025-05-20T21:09:16.321+00:00",
      "type": "ActionResources",
      "description": "Musical Chairs used scum to take action.",
      "value": 1
    },
    {
      "id": "HJ3Y_",
      "timestamp": "2025-05-20T21:09:17.399+00:00",
      "type": "SocietyActionsTaken",
      "description": "Frog house",
      "value": 1
    },
    {
      "id": "z_62n",
      "timestamp": "2025-05-20T21:09:17.399+00:00",
      "type": "ActionResources",
      "description": "Frog house used feral cats,righteous anger to take action.",
      "value": 2
    },
    {
      "id": "i-zrS",
      "timestamp": "2025-05-20T21:09:17.399+00:00",
      "type": "SocietyActionsTaken",
      "description": "Toad Shack",
      "value": 0
    },
    {
      "id": "y_0qu",
      "timestamp": "2025-05-20T21:09:17.399+00:00",
      "type": "SocietyActionsTaken",
      "description": "Beetle Junkies",
      "value": 2
    },
    {
      "id": "xUI1c",
      "timestamp": "2025-05-20T21:09:17.400+00:00",
      "type": "ActionResources",
      "description": "Beetle Junkies used hey now to take action.",
      "value": 1
    },
    {
      "id": "IhWAQ",
      "timestamp": "2025-05-20T21:09:17.400+00:00",
      "type": "ActionResources",
      "description": "Beetle Junkies used hey now,bytes to take action.",
      "value": 2
    },
    {
      "id": "YoQJk",
      "timestamp": "2025-05-20T21:09:17.400+00:00",
      "type": "SocietyActionsTaken",
      "description": "Better Burritos",
      "value": 0
    },
    {
      "id": "Bp7RM",
      "timestamp": "2025-05-20T21:09:17.400+00:00",
      "type": "SocietyActionsTaken",
      "description": "Musical Chairs",
      "value": 1
    },
    {
      "id": "gjBJR",
      "timestamp": "2025-05-20T21:09:17.400+00:00",
      "type": "ActionResources",
      "description": "Musical Chairs used scum to take action.",
      "value": 1
    },
    {
      "id": "fVVgB",
      "timestamp": "2025-05-20T21:09:18.672+00:00",
      "type": "SocietyActionsTaken",
      "description": "Frog house",
      "value": 1
    },
    {
      "id": "D83zQ",
      "timestamp": "2025-05-20T21:09:18.672+00:00",
      "type": "ActionResources",
      "description": "Frog house used feral cats,righteous anger to take action.",
      "value": 2
    },
    {
      "id": "X6N5B",
      "timestamp": "2025-05-20T21:09:18.672+00:00",
      "type": "SocietyActionsTaken",
      "description": "Toad Shack",
      "value": 0
    },
    {
      "id": "XvrOO",
      "timestamp": "2025-05-20T21:09:18.672+00:00",
      "type": "SocietyActionsTaken",
      "description": "Beetle Junkies",
      "value": 2
    },
    {
      "id": "dc--6",
      "timestamp": "2025-05-20T21:09:18.672+00:00",
      "type": "ActionResources",
      "description": "Beetle Junkies used hey now to take action.",
      "value": 1
    },
    {
      "id": "PrIJW",
      "timestamp": "2025-05-20T21:09:18.672+00:00",
      "type": "ActionResources",
      "description": "Beetle Junkies used hey now,bytes to take action.",
      "value": 2
    },
    {
      "id": "mBTfF",
      "timestamp": "2025-05-20T21:09:18.672+00:00",
      "type": "SocietyActionsTaken",
      "description": "Better Burritos",
      "value": 0
    },
    {
      "id": "NgRNb",
      "timestamp": "2025-05-20T21:09:18.672+00:00",
      "type": "SocietyActionsTaken",
      "description": "Musical Chairs",
      "value": 1
    },
    {
      "id": "zad-j",
      "timestamp": "2025-05-20T21:09:18.672+00:00",
      "type": "ActionResources",
      "description": "Musical Chairs used scum to take action.",
      "value": 1
    },
    {
      "id": "QaH_b",
      "timestamp": "2025-05-20T21:11:32.598+00:00",
      "type": "SocietyActionsTaken",
      "description": "Frog house",
      "value": 0
    },
    {
      "id": "KjKMr",
      "timestamp": "2025-05-20T21:11:32.598+00:00",
      "type": "SocietyActionsTaken",
      "description": "Toad Shack",
      "value": 0
    },
    {
      "id": "P-d3F",
      "timestamp": "2025-05-20T21:11:32.598+00:00",
      "type": "SocietyActionsTaken",
      "description": "Beetle Junkies",
      "value": 0
    },
    {
      "id": "XuBnh",
      "timestamp": "2025-05-20T21:11:32.599+00:00",
      "type": "SocietyActionsTaken",
      "description": "Better Burritos",
      "value": 0
    },
    {
      "id": "g2eBF",
      "timestamp": "2025-05-20T21:11:32.599+00:00",
      "type": "SocietyActionsTaken",
      "description": "Musical Chairs",
      "value": 0
    },
    {
      "id": "IyW_e",
      "timestamp": "2025-05-20T21:12:00.439+00:00",
      "type": "PhaseStarted",
      "description": "Round 2: Galactic Phase",
      "value": "2025-05-20T21:12:00.439+00:00"
    },
    {
      "id": "E_TPy",
      "timestamp": "2025-05-20T21:12:03.821+00:00",
      "type": "PhaseStarted",
      "description": "Round 2: Galactic Phase",
      "value": "2025-05-20T21:12:03.821+00:00"
    },
    {
      "id": "DAyr0",
      "timestamp": "2025-05-20T21:13:10.220+00:00",
      "type": "PhaseStarted",
      "description": "Round 2: Galactic Phase",
      "value": "2025-05-20T21:13:10.220+00:00"
    },
    {
      "id": "bgi_-",
      "timestamp": "2025-05-20T21:13:18.473+00:00",
      "type": "PhaseStarted",
      "description": "Round 2: Galactic Phase",
      "value": "2025-05-20T21:13:18.473+00:00"
    },
    {
      "id": "Ws-aS",
      "timestamp": "2025-05-20T21:13:20.937+00:00",
      "type": "PhaseEnded",
      "description": "Round 2: Galactic Phase",
      "value": "2025-05-20T21:13:20.937+00:00"
    },
    {
      "id": "uDoJB",
      "timestamp": "2025-05-20T21:13:20.937+00:00",
      "type": "PhaseDuration",
      "description": "Round 2: Galactic Phase",
      "value": 0.04106666666666667
    },
    {
      "id": "lbo6r",
      "timestamp": "2025-05-20T21:13:24.192+00:00",
      "type": "PhaseStarted",
      "description": "Round 2: Societal Phase",
      "value": "2025-05-20T21:13:24.192+00:00"
    },
    {
      "id": "nDwzZ",
      "timestamp": "2025-05-20T21:16:40.690+00:00",
      "type": "ResourceCreated",
      "value": "wgrtgrtgw"
    },
    {
      "id": "HKpWl",
      "timestamp": "2025-05-20T21:16:47.347+00:00",
      "type": "ResourceCreated",
      "value": "gwgwrtgwrt"
    },
    {
      "id": "Gh3vO",
      "timestamp": "2025-05-20T23:35:24.461+00:00",
      "type": "PhaseStarted",
      "description": "Round 2: Societal Phase",
      "value": "2025-05-20T23:35:24.461+00:00"
    },
    {
      "id": "e0dgf",
      "timestamp": "2025-05-23T21:10:32.131+00:00",
      "type": "SocietyActionsTaken",
      "description": "Frog house",
      "value": 1
    },
    {
      "id": "YgQL2",
      "timestamp": "2025-05-23T21:10:32.132+00:00",
      "type": "ActionResources",
      "description": "Frog house used feral cats,righteous anger to take action.",
      "value": 2
    },
    {
      "id": "mxCPc",
      "timestamp": "2025-05-23T21:10:32.132+00:00",
      "type": "SocietyActionsTaken",
      "description": "Toad Shack",
      "value": 0
    },
    {
      "id": "TzZV_",
      "timestamp": "2025-05-23T21:10:32.132+00:00",
      "type": "SocietyActionsTaken",
      "description": "Beetle Junkies",
      "value": 5
    },
    {
      "id": "TJAb_",
      "timestamp": "2025-05-23T21:10:32.132+00:00",
      "type": "ActionResources",
      "description": "Beetle Junkies used hey now to take action.",
      "value": 1
    },
    {
      "id": "Sdtn0",
      "timestamp": "2025-05-23T21:10:32.132+00:00",
      "type": "ActionResources",
      "description": "Beetle Junkies used hey now,bytes to take action.",
      "value": 2
    },
    {
      "id": "UTto1",
      "timestamp": "2025-05-23T21:10:32.132+00:00",
      "type": "ActionResources",
      "description": "Beetle Junkies used bytes to take action.",
      "value": 1
    },
    {
      "id": "TcD4W",
      "timestamp": "2025-05-23T21:10:32.132+00:00",
      "type": "ActionResources",
      "description": "Beetle Junkies used adfasd,bytes to take action.",
      "value": 2
    },
    {
      "id": "l7sFr",
      "timestamp": "2025-05-23T21:10:32.132+00:00",
      "type": "ActionResources",
      "description": "Beetle Junkies used blergh to take action.",
      "value": 1
    },
    {
      "id": "rEDZP",
      "timestamp": "2025-05-23T21:10:32.132+00:00",
      "type": "SocietyActionsTaken",
      "description": "Better Burritos",
      "value": 0
    },
    {
      "id": "HtWU6",
      "timestamp": "2025-05-23T21:10:32.132+00:00",
      "type": "SocietyActionsTaken",
      "description": "Musical Chairs",
      "value": 1
    },
    {
      "id": "QkybF",
      "timestamp": "2025-05-23T21:10:32.132+00:00",
      "type": "ActionResources",
      "description": "Musical Chairs used scum to take action.",
      "value": 1
    },
    {
      "id": "tkHKO",
      "timestamp": "2025-05-23T21:10:33.325+00:00",
      "type": "PhaseStarted",
      "description": "Round 3: Universal Phase",
      "value": "2025-05-23T21:10:33.325+00:00"
    },
    {
      "id": "hnqBL",
      "timestamp": "2025-05-23T21:10:33.326+00:00",
      "type": "CommunitiesEndangered",
      "description": "New Episode: Lapiz,nana,baba,popo,skreeee",
      "value": 5
    },
    {
      "id": "wCTs2",
      "timestamp": "2025-05-23T21:13:40.258+00:00",
      "type": "SocietyActionsTaken",
      "description": "Frog house",
      "value": 1
    },
    {
      "id": "tvrJQ",
      "timestamp": "2025-05-23T21:13:40.259+00:00",
      "type": "ActionResources",
      "description": "Frog house used feral cats,righteous anger to take action.",
      "value": 2
    },
    {
      "id": "nKcJU",
      "timestamp": "2025-05-23T21:13:40.259+00:00",
      "type": "SocietyActionsTaken",
      "description": "Toad Shack",
      "value": 0
    },
    {
      "id": "GcnVK",
      "timestamp": "2025-05-23T21:13:40.259+00:00",
      "type": "SocietyActionsTaken",
      "description": "Beetle Junkies",
      "value": 5
    },
    {
      "id": "mtrUX",
      "timestamp": "2025-05-23T21:13:40.259+00:00",
      "type": "ActionResources",
      "description": "Beetle Junkies used hey now to take action.",
      "value": 1
    },
    {
      "id": "MaP_7",
      "timestamp": "2025-05-23T21:13:40.259+00:00",
      "type": "ActionResources",
      "description": "Beetle Junkies used hey now,bytes to take action.",
      "value": 2
    },
    {
      "id": "JYKr2",
      "timestamp": "2025-05-23T21:13:40.259+00:00",
      "type": "ActionResources",
      "description": "Beetle Junkies used bytes to take action.",
      "value": 1
    },
    {
      "id": "prmBi",
      "timestamp": "2025-05-23T21:13:40.259+00:00",
      "type": "ActionResources",
      "description": "Beetle Junkies used adfasd,bytes to take action.",
      "value": 2
    },
    {
      "id": "in4ep",
      "timestamp": "2025-05-23T21:13:40.259+00:00",
      "type": "ActionResources",
      "description": "Beetle Junkies used blergh to take action.",
      "value": 1
    },
    {
      "id": "oEgim",
      "timestamp": "2025-05-23T21:13:40.259+00:00",
      "type": "SocietyActionsTaken",
      "description": "Better Burritos",
      "value": 0
    },
    {
      "id": "w8qhE",
      "timestamp": "2025-05-23T21:13:40.259+00:00",
      "type": "SocietyActionsTaken",
      "description": "Musical Chairs",
      "value": 1
    },
    {
      "id": "PnfW6",
      "timestamp": "2025-05-23T21:13:40.259+00:00",
      "type": "ActionResources",
      "description": "Musical Chairs used scum to take action.",
      "value": 1
    },
    {
      "id": "PjQZe",
      "timestamp": "2025-05-23T22:07:31.953+00:00",
      "type": "SocietyActionsTaken",
      "description": "Frog house",
      "value": 1
    },
    {
      "id": "gJzBO",
      "timestamp": "2025-05-23T22:07:31.953+00:00",
      "type": "ActionResources",
      "description": "Frog house used  to take action.",
      "value": 0
    },
    {
      "id": "MX4r8",
      "timestamp": "2025-05-23T22:07:31.953+00:00",
      "type": "SocietyActionsTaken",
      "description": "Toad Shack",
      "value": 0
    },
    {
      "id": "E4Kzc",
      "timestamp": "2025-05-23T22:07:31.953+00:00",
      "type": "SocietyActionsTaken",
      "description": "Beetle Junkies",
      "value": 1
    },
    {
      "id": "fnJpv",
      "timestamp": "2025-05-23T22:07:31.954+00:00",
      "type": "ActionResources",
      "description": "Beetle Junkies used gwgwrtgwrt,new to take action.",
      "value": 2
    },
    {
      "id": "ejhAw",
      "timestamp": "2025-05-23T22:07:31.954+00:00",
      "type": "SocietyActionsTaken",
      "description": "Better Burritos",
      "value": 0
    },
    {
      "id": "yKk5f",
      "timestamp": "2025-05-23T22:07:31.954+00:00",
      "type": "SocietyActionsTaken",
      "description": "Musical Chairs",
      "value": 1
    },
    {
      "id": "yiPIb",
      "timestamp": "2025-05-23T22:07:31.954+00:00",
      "type": "ActionResources",
      "description": "Musical Chairs used  to take action.",
      "value": 0
    },
    {
      "id": "Ds0CM",
      "timestamp": "2025-05-23T22:07:41.942+00:00",
      "type": "SocietyActionsTaken",
      "description": "Frog house",
      "value": 1
    },
    {
      "id": "GlPdG",
      "timestamp": "2025-05-23T22:07:41.943+00:00",
      "type": "ActionResources",
      "description": "Frog house used  to take action.",
      "value": 0
    },
    {
      "id": "rCo28",
      "timestamp": "2025-05-23T22:07:41.943+00:00",
      "type": "SocietyActionsTaken",
      "description": "Toad Shack",
      "value": 0
    },
    {
      "id": "NRgEW",
      "timestamp": "2025-05-23T22:07:41.943+00:00",
      "type": "SocietyActionsTaken",
      "description": "Beetle Junkies",
      "value": 1
    },
    {
      "id": "dv4_P",
      "timestamp": "2025-05-23T22:07:41.943+00:00",
      "type": "ActionResources",
      "description": "Beetle Junkies used gwgwrtgwrt,new to take action.",
      "value": 2
    },
    {
      "id": "jj-9y",
      "timestamp": "2025-05-23T22:07:41.943+00:00",
      "type": "SocietyActionsTaken",
      "description": "Better Burritos",
      "value": 0
    },
    {
      "id": "nbZl3",
      "timestamp": "2025-05-23T22:07:41.943+00:00",
      "type": "SocietyActionsTaken",
      "description": "Musical Chairs",
      "value": 1
    },
    {
      "id": "sN9tv",
      "timestamp": "2025-05-23T22:07:41.943+00:00",
      "type": "ActionResources",
      "description": "Musical Chairs used  to take action.",
      "value": 0
    },
    {
      "id": "wfHa1",
      "timestamp": "2025-05-23T22:07:46.977+00:00",
      "type": "PhaseStarted",
      "description": "Round 3: Universal Phase",
      "value": "2025-05-23T22:07:46.977+00:00"
    },
    {
      "id": "roFTY",
      "timestamp": "2025-05-23T22:07:46.978+00:00",
      "type": "CommunitiesEndangered",
      "description": "New Episode: Lapiz,nana,baba,popo,skreeee",
      "value": 5
    },
    {
      "id": "O7zJV",
      "timestamp": "2025-05-24T03:26:28.661+00:00",
      "type": "PhaseStarted",
      "description": "Round 3: Universal Phase",
      "value": "2025-05-24T03:26:28.661+00:00"
    },
    {
      "id": "ACBUf",
      "timestamp": "2025-05-24T03:26:28.662+00:00",
      "type": "CommunitiesEndangered",
      "description": "New Episode: Lapiz,nana,baba,popo,skreeee",
      "value": 5
    },
    {
      "id": "G4hl_",
      "timestamp": "2025-05-24T03:30:00.987+00:00",
      "type": "SocietyActionsTaken",
      "description": "Frog house",
      "value": 0
    },
    {
      "id": "kLif9",
      "timestamp": "2025-05-24T03:30:00.987+00:00",
      "type": "SocietyActionsTaken",
      "description": "Toad Shack",
      "value": 0
    },
    {
      "id": "xpuef",
      "timestamp": "2025-05-24T03:30:00.987+00:00",
      "type": "SocietyActionsTaken",
      "description": "Beetle Junkies",
      "value": 0
    },
    {
      "id": "P_Poo",
      "timestamp": "2025-05-24T03:30:00.987+00:00",
      "type": "SocietyActionsTaken",
      "description": "Better Burritos",
      "value": 0
    },
    {
      "id": "tvBGy",
      "timestamp": "2025-05-24T03:30:00.987+00:00",
      "type": "SocietyActionsTaken",
      "description": "Musical Chairs",
      "value": 0
    },
    {
      "id": "z1VE1",
      "timestamp": "2025-05-24T03:30:03.746+00:00",
      "type": "SocietyActionsTaken",
      "description": "Frog house",
      "value": 1
    },
    {
      "id": "PqSCj",
      "timestamp": "2025-05-24T03:30:03.747+00:00",
      "type": "ActionResources",
      "description": "Frog house used  to take action.",
      "value": 0
    },
    {
      "id": "Gkc8Y",
      "timestamp": "2025-05-24T03:30:03.747+00:00",
      "type": "SocietyActionsTaken",
      "description": "Toad Shack",
      "value": 0
    },
    {
      "id": "UIo5N",
      "timestamp": "2025-05-24T03:30:03.747+00:00",
      "type": "SocietyActionsTaken",
      "description": "Beetle Junkies",
      "value": 1
    },
    {
      "id": "GcGKs",
      "timestamp": "2025-05-24T03:30:03.747+00:00",
      "type": "ActionResources",
      "description": "Beetle Junkies used gwgwrtgwrt,new to take action.",
      "value": 2
    },
    {
      "id": "xjYRa",
      "timestamp": "2025-05-24T03:30:03.747+00:00",
      "type": "SocietyActionsTaken",
      "description": "Better Burritos",
      "value": 0
    },
    {
      "id": "xVX66",
      "timestamp": "2025-05-24T03:30:03.748+00:00",
      "type": "SocietyActionsTaken",
      "description": "Musical Chairs",
      "value": 1
    },
    {
      "id": "scdUW",
      "timestamp": "2025-05-24T03:30:03.748+00:00",
      "type": "ActionResources",
      "description": "Musical Chairs used  to take action.",
      "value": 0
    },
    {
      "id": "tzU_R",
      "timestamp": "2025-05-26T00:06:55.382+00:00",
      "type": "PhaseStarted",
      "description": "Round 3: Galactic Phase",
      "value": "2025-05-26T00:06:55.382+00:00"
    },
    {
      "id": "eZxt9",
      "timestamp": "2025-05-26T00:06:59.241+00:00",
      "type": "SocietyActionsTaken",
      "description": "Frog house",
      "value": 1
    },
    {
      "id": "vdqz_",
      "timestamp": "2025-05-26T00:06:59.241+00:00",
      "type": "ActionResources",
      "description": "Frog house used righteous anger to take action.",
      "value": 1
    },
    {
      "id": "rpo4a",
      "timestamp": "2025-05-26T00:06:59.242+00:00",
      "type": "SocietyActionsTaken",
      "description": "Toad Shack",
      "value": 0
    },
    {
      "id": "mJJCh",
      "timestamp": "2025-05-26T00:06:59.242+00:00",
      "type": "SocietyActionsTaken",
      "description": "Beetle Junkies",
      "value": 0
    },
    {
      "id": "qR4TY",
      "timestamp": "2025-05-26T00:06:59.242+00:00",
      "type": "SocietyActionsTaken",
      "description": "Better Burritos",
      "value": 0
    },
    {
      "id": "yfN3F",
      "timestamp": "2025-05-26T00:06:59.242+00:00",
      "type": "SocietyActionsTaken",
      "description": "Musical Chairs",
      "value": 0
    },
    {
      "id": "McI_E",
      "timestamp": "2025-05-28T15:36:19.218Z",
      "type": "PhaseStarted",
      "description": "Round 4: Galactic Phase",
      "value": "2025-05-28T15:36:19.218Z"
    },
    {
      "id": "vm4lj",
      "timestamp": "2025-05-28T15:36:28.110Z",
      "type": "PhaseStarted",
      "description": "Round 2: Individual Phase",
      "value": "2025-05-28T15:36:28.110Z"
    },
    {
      "id": "jiAMm",
      "timestamp": "2025-05-28T15:36:29.116Z",
      "type": "PhaseEnded",
      "description": "Round 2: Individual Phase",
      "value": "2025-05-28T15:36:29.116Z"
    },
    {
      "id": "kJh8f",
      "timestamp": "2025-05-28T15:36:29.116Z",
      "type": "PhaseDuration",
      "description": "Round 2: Individual Phase",
      "value": 0.016783333333333334
    },
    {
      "id": "Gd-4B",
      "timestamp": "2025-05-28T15:36:35.676Z",
      "type": "SocietyActionsTaken",
      "description": "Frog house",
      "value": 1
    },
    {
      "id": "w4zY3",
      "timestamp": "2025-05-28T15:36:35.676Z",
      "type": "ActionResources",
      "description": "Frog house used righteous anger,feral cats to take action.",
      "value": 2
    },
    {
      "id": "JX8Qa",
      "timestamp": "2025-05-28T15:36:35.676Z",
      "type": "SocietyActionsTaken",
      "description": "Toad Shack",
      "value": 0
    },
    {
      "id": "BPDUQ",
      "timestamp": "2025-05-28T15:36:35.676Z",
      "type": "SocietyActionsTaken",
      "description": "Beetle Junkies",
      "value": 1
    },
    {
      "id": "Rs_Ia",
      "timestamp": "2025-05-28T15:36:35.676Z",
      "type": "ActionResources",
      "description": "Beetle Junkies used gwgwrtgwrt,new to take action.",
      "value": 2
    },
    {
      "id": "ZKKvF",
      "timestamp": "2025-05-28T15:36:35.676Z",
      "type": "SocietyActionsTaken",
      "description": "Better Burritos",
      "value": 0
    },
    {
      "id": "w4LAJ",
      "timestamp": "2025-05-28T15:36:35.676Z",
      "type": "SocietyActionsTaken",
      "description": "Musical Chairs",
      "value": 1
    },
    {
      "id": "UOGpo",
      "timestamp": "2025-05-28T15:36:35.676Z",
      "type": "ActionResources",
      "description": "Musical Chairs used  to take action.",
      "value": 0
    },
    {
      "id": "ZEZVc",
      "timestamp": "2025-05-28T15:37:14.486Z",
      "type": "PhaseStarted",
      "description": "Round 3: Universal Phase",
      "value": "2025-05-28T15:37:14.486Z"
    },
    {
      "id": "MRn07",
      "timestamp": "2025-05-28T15:37:14.486Z",
      "type": "CommunitiesEndangered",
      "description": "New Episode: skreeee,My Guys",
      "value": 2
    },
    {
      "id": "cxDv0",
      "timestamp": "2025-05-28T15:37:16.089Z",
      "type": "PhaseEnded",
      "description": "Round 3: Universal Phase",
      "value": "2025-05-28T15:37:16.089Z"
    },
    {
      "id": "vTImf",
      "timestamp": "2025-05-28T15:37:16.089Z",
      "type": "PhaseDuration",
      "description": "Round 3: Universal Phase",
      "value": 0.026716666666666666
    },
    {
      "id": "O2nFy",
      "timestamp": "2025-05-28T15:39:29.046Z",
      "type": "PhaseStarted",
      "description": "Round 2: Galactic Phase",
      "value": "2025-05-28T15:39:29.046Z"
    },
    {
      "id": "wF60k",
      "timestamp": "2025-05-28T15:49:43.536Z",
      "type": "PhaseEnded",
      "description": "Round 2: Galactic Phase",
      "value": "2025-05-28T15:49:43.536Z"
    },
    {
      "id": "w7QzX",
      "timestamp": "2025-05-28T15:49:43.536Z",
      "type": "PhaseDuration",
      "description": "Round 2: Galactic Phase",
      "value": 10.241516666666667
    },
    {
      "id": "Xvf4P",
      "timestamp": "2025-05-28T16:04:19.905Z",
      "type": "PhaseStarted",
      "description": "Round 2: Individual Phase",
      "value": "2025-05-28T16:04:19.905Z"
    },
    {
      "id": "p3hhY",
      "timestamp": "2025-05-28T16:04:38.231Z",
      "type": "PhaseStarted",
      "description": "Round 2: Galactic Phase",
      "value": "2025-05-28T16:04:38.231Z"
    },
    {
      "id": "HJp4v",
      "timestamp": "2025-05-28T16:04:41.850Z",
      "type": "PhaseEnded",
      "description": "Round 2: Galactic Phase",
      "value": "2025-05-28T16:04:41.850Z"
    },
    {
      "id": "Bvd1Z",
      "timestamp": "2025-05-28T16:04:41.851Z",
      "type": "PhaseDuration",
      "description": "Round 2: Galactic Phase",
      "value": 0.060316666666666664
    },
    {
      "id": "Xv8WJ",
      "timestamp": "2025-05-28T16:04:43.099Z",
      "type": "PhaseEnded",
      "description": "Round 2: Individual Phase",
      "value": "2025-05-28T16:04:43.099Z"
    },
    {
      "id": "IKPzF",
      "timestamp": "2025-05-28T16:04:43.099Z",
      "type": "PhaseDuration",
      "description": "Round 2: Individual Phase",
      "value": 0.38656666666666667
    },
    {
      "id": "m7pBv",
      "timestamp": "2025-05-28T16:04:45.245Z",
      "type": "PhaseStarted",
      "description": "Round 2: Break",
      "value": "2025-05-28T16:04:45.245Z"
    },
    {
      "id": "d6toj",
      "timestamp": "2025-05-28T16:04:45.934Z",
      "type": "PhaseEnded",
      "description": "Round 2: Break",
      "value": "2025-05-28T16:04:45.934Z"
    },
    {
      "id": "vUqy0",
      "timestamp": "2025-05-28T16:04:45.934Z",
      "type": "PhaseDuration",
      "description": "Round 2: Break",
      "value": 0.0115
    },
    {
      "id": "xza8c",
      "timestamp": "2025-05-28T16:04:45.935Z",
      "type": "SocietyActionsTaken",
      "description": "Frog house",
      "value": 1
    },
    {
      "id": "pHpkO",
      "timestamp": "2025-05-28T16:04:45.935Z",
      "type": "ActionResources",
      "description": "Frog house used righteous anger,feral cats to take action.",
      "value": 2
    },
    {
      "id": "r89oh",
      "timestamp": "2025-05-28T16:04:45.935Z",
      "type": "SocietyActionsTaken",
      "description": "Toad Shack",
      "value": 0
    },
    {
      "id": "n_UFP",
      "timestamp": "2025-05-28T16:04:45.935Z",
      "type": "SocietyActionsTaken",
      "description": "Beetle Junkies",
      "value": 1
    },
    {
      "id": "B7TZj",
      "timestamp": "2025-05-28T16:04:45.935Z",
      "type": "ActionResources",
      "description": "Beetle Junkies used gwgwrtgwrt,new to take action.",
      "value": 2
    },
    {
      "id": "TAjE4",
      "timestamp": "2025-05-28T16:04:45.935Z",
      "type": "SocietyActionsTaken",
      "description": "Better Burritos",
      "value": 0
    },
    {
      "id": "pRwEJ",
      "timestamp": "2025-05-28T16:04:45.935Z",
      "type": "SocietyActionsTaken",
      "description": "Musical Chairs",
      "value": 1
    },
    {
      "id": "YCl3E",
      "timestamp": "2025-05-28T16:04:45.935Z",
      "type": "ActionResources",
      "description": "Musical Chairs used  to take action.",
      "value": 0
    },
    {
      "id": "Y6pod",
      "timestamp": "2025-05-28T16:10:00.811Z",
      "type": "SocietyActionsTaken",
      "description": "Frog house",
      "value": 1
    },
    {
      "id": "EEpQY",
      "timestamp": "2025-05-28T16:10:00.811Z",
      "type": "ActionResources",
      "description": "Frog house used righteous anger,feral cats to take action.",
      "value": 2
    },
    {
      "id": "oM5hY",
      "timestamp": "2025-05-28T16:10:00.811Z",
      "type": "SocietyActionsTaken",
      "description": "Toad Shack",
      "value": 0
    },
    {
      "id": "sJLyz",
      "timestamp": "2025-05-28T16:10:00.811Z",
      "type": "SocietyActionsTaken",
      "description": "Beetle Junkies",
      "value": 1
    },
    {
      "id": "GWwDu",
      "timestamp": "2025-05-28T16:10:00.811Z",
      "type": "ActionResources",
      "description": "Beetle Junkies used gwgwrtgwrt,new to take action.",
      "value": 2
    },
    {
      "id": "jqOhE",
      "timestamp": "2025-05-28T16:10:00.811Z",
      "type": "SocietyActionsTaken",
      "description": "Better Burritos",
      "value": 0
    },
    {
      "id": "EOhGy",
      "timestamp": "2025-05-28T16:10:00.811Z",
      "type": "SocietyActionsTaken",
      "description": "Musical Chairs",
      "value": 1
    },
    {
      "id": "TBcti",
      "timestamp": "2025-05-28T16:10:00.811Z",
      "type": "ActionResources",
      "description": "Musical Chairs used  to take action.",
      "value": 0
    },
    {
      "id": "VtMOH",
      "timestamp": "2025-05-28T16:33:10.602Z",
      "type": "PhaseStarted",
      "description": "Round 3: Universal Phase",
      "value": "2025-05-28T16:33:10.602Z"
    },
    {
      "id": "iPlSH",
      "timestamp": "2025-05-28T16:33:10.602Z",
      "type": "CommunitiesEndangered",
      "description": "New Episode: skreeee,My Guys",
      "value": 2
    },
    {
      "id": "iYphe",
      "timestamp": "2025-05-28T16:33:21.174Z",
      "type": "PhaseStarted",
      "description": "Round 2: Individual Phase",
      "value": "2025-05-28T16:33:21.174Z"
    },
    {
      "id": "FhuXs",
      "timestamp": "2025-05-28T19:09:05.416Z",
      "type": "PhaseStarted",
      "description": "Round 2: Individual Phase",
      "value": "2025-05-28T19:09:05.416Z"
    },
    {
      "id": "BRsMV",
      "timestamp": "2025-05-28T19:11:19.810Z",
      "type": "ResourceCreated",
      "value": "Hello"
    },
    {
      "id": "Qkib5",
      "timestamp": "2025-05-28T19:19:02.729Z",
      "type": "ResourceCreated",
      "value": "toads"
    },
    {
      "id": "s4ZQB",
      "timestamp": "2025-05-28T19:20:31.073Z",
      "type": "PhaseStarted",
      "description": "Round 2: Individual Phase",
      "value": "2025-05-28T19:20:31.073Z"
    },
    {
      "id": "il_2i",
      "timestamp": "2025-05-28T19:20:33.405Z",
      "type": "PhaseEnded",
      "description": "Round 2: Individual Phase",
      "value": "2025-05-28T19:20:33.405Z"
    },
    {
      "id": "wivOR",
      "timestamp": "2025-05-28T19:20:33.405Z",
      "type": "PhaseDuration",
      "description": "Round 2: Individual Phase",
      "value": 0.03886666666666667
    },
    {
      "id": "w4Q55",
      "timestamp": "2025-05-28T19:22:46.449Z",
      "type": "PhaseStarted",
      "description": "Round 0: Setup/Onboarding",
      "value": "2025-05-28T19:22:46.449Z"
    },
    {
      "id": "lMn_T",
      "timestamp": "2025-05-28T19:23:14.505Z",
      "type": "PhaseEnded",
      "description": "Round 0: Setup/Onboarding",
      "value": "2025-05-28T19:23:14.505Z"
    },
    {
      "id": "BcgZh",
      "timestamp": "2025-05-28T19:23:14.506Z",
      "type": "PhaseDuration",
      "description": "Round 0: Setup/Onboarding",
      "value": 0.4676
    },
    {
      "id": "ESBs1",
      "timestamp": "2025-05-28T19:23:14.506Z",
      "type": "SocietyActionsTaken",
      "description": "Frog house",
      "value": 0
    },
    {
      "id": "vDl98",
      "timestamp": "2025-05-28T19:23:14.506Z",
      "type": "SocietyActionsTaken",
      "description": "Toad Shack",
      "value": 0
    },
    {
      "id": "MQc2n",
      "timestamp": "2025-05-28T19:23:14.506Z",
      "type": "SocietyActionsTaken",
      "description": "Beetle Junkies",
      "value": 0
    },
    {
      "id": "vazmE",
      "timestamp": "2025-05-28T19:23:14.506Z",
      "type": "SocietyActionsTaken",
      "description": "Better Burritos",
      "value": 0
    },
    {
      "id": "qvfwk",
      "timestamp": "2025-05-28T19:23:14.506Z",
      "type": "SocietyActionsTaken",
      "description": "Musical Chairs",
      "value": 0
    },
    {
      "id": "xzgLW",
      "timestamp": "2025-05-28T19:23:14.506Z",
      "type": "SocietyActionsTaken",
      "description": "Sibby",
      "value": 0
    },
    {
      "id": "imawU",
      "timestamp": "2025-05-28T19:23:16.636Z",
      "type": "PhaseStarted",
      "description": "Round 1: Galactic Phase",
      "value": "2025-05-28T19:23:16.636Z"
    },
    {
      "id": "RynCz",
      "timestamp": "2025-05-28T19:23:58.655Z",
      "type": "PhaseEnded",
      "description": "Round 1: Galactic Phase",
      "value": "2025-05-28T19:23:58.655Z"
    },
    {
      "id": "nwtbE",
      "timestamp": "2025-05-28T19:23:58.655Z",
      "type": "PhaseDuration",
      "description": "Round 1: Galactic Phase",
      "value": 0.7003166666666667
    },
    {
      "id": "MLBDj",
      "timestamp": "2025-05-28T19:23:58.655Z",
      "type": "SocietyActionsTaken",
      "description": "Frog house",
      "value": 0
    },
    {
      "id": "UcQj8",
      "timestamp": "2025-05-28T19:23:58.655Z",
      "type": "SocietyActionsTaken",
      "description": "Toad Shack",
      "value": 0
    },
    {
      "id": "InM6a",
      "timestamp": "2025-05-28T19:23:58.655Z",
      "type": "SocietyActionsTaken",
      "description": "Beetle Junkies",
      "value": 0
    },
    {
      "id": "veCWx",
      "timestamp": "2025-05-28T19:23:58.655Z",
      "type": "SocietyActionsTaken",
      "description": "Better Burritos",
      "value": 0
    },
    {
      "id": "U-m5A",
      "timestamp": "2025-05-28T19:23:58.655Z",
      "type": "SocietyActionsTaken",
      "description": "Musical Chairs",
      "value": 0
    },
    {
      "id": "DFKr0",
      "timestamp": "2025-05-28T19:23:58.655Z",
      "type": "SocietyActionsTaken",
      "description": "Sibby",
      "value": 0
    },
    {
      "id": "tLLZ0",
      "timestamp": "2025-05-28T19:24:05.025Z",
      "type": "SocietyActionsTaken",
      "description": "Frog house",
      "value": 0
    },
    {
      "id": "KGw9D",
      "timestamp": "2025-05-28T19:24:05.025Z",
      "type": "SocietyActionsTaken",
      "description": "Toad Shack",
      "value": 0
    },
    {
      "id": "BIdsX",
      "timestamp": "2025-05-28T19:24:05.025Z",
      "type": "SocietyActionsTaken",
      "description": "Beetle Junkies",
      "value": 0
    },
    {
      "id": "ieOMo",
      "timestamp": "2025-05-28T19:24:05.025Z",
      "type": "SocietyActionsTaken",
      "description": "Better Burritos",
      "value": 0
    },
    {
      "id": "xtuas",
      "timestamp": "2025-05-28T19:24:05.025Z",
      "type": "SocietyActionsTaken",
      "description": "Musical Chairs",
      "value": 0
    },
    {
      "id": "gRhkg",
      "timestamp": "2025-05-28T19:24:05.025Z",
      "type": "SocietyActionsTaken",
      "description": "Sibby",
      "value": 0
    }
  ]
}